src/defs.vh
`define OP_SW      32'b00000000000000000010000000100011
`define MASK_OP_SW 32'b00000000000000000111000001111111

`define OP_LW      32'b00000000000000000010000000000011
`define MASK_OP_LW 32'b00000000000000000111000001111111

`define OP_LUI      32'b00000000000000000000000000110111
`define MASK_OP_LUI 32'b00000000000000000000000001111111

`define OP_ADDI      32'b00000000000000000000000000010011
`define MASK_OP_ADDI 32'b00000000000000000111000001111111

src/core.v
`include "defs.vh"

module CORE(
    input clock,

// UART
    output tx_start,
    output [7:0] tx_data,

// Memory
    output [31:0] raddr,
    output [31:0] iaddr,
    output wen,
    output [31:0] wdata,
    input [31:0] inst,
    input [31:0] rdata
);

    reg [31:0] register [31:0];
    reg [31:0] REGISTER_TEST;

    reg [7:0] reg_tx_data;
    reg reg_tx_start;

    reg [31:0] pc;
    reg [31:0] pc_p4;
    reg [31:0] reg_inst;
    reg [31:0] reg_iaddr;
    reg [31:0] reg_raddr;
    reg [31:0] reg_wdata;
    reg reg_wen;

    reg [31:0] reg_wb_data;
    reg reg_wb_wen;

    reg [6:0] opcode;
    reg [4:0] rd;
    reg [2:0] funct3;
    reg [4:0] rs1;
    reg [4:0] rs2;
    reg [6:0] funct7;

    wire [31:0] rs1_data;
    wire [31:0] rs2_data;

    reg [11:0] i_imm;
    wire [31:0] i_imm_sext;
    reg [11:0] s_imm;
    wire [31:0] s_imm_sext;
    reg [12:0] b_imm;
    reg [31:0] u_imm;
    reg [20:0] j_imm;

    reg [31:0] alu_out;

    localparam ST_IF = 0;
    localparam ST_ID = 1;
    localparam ST_EX = 2;
    localparam ST_ACCESS = 3;
    localparam ST_WB = 4;
    reg [3:0] stage;

    integer i;
    initial begin
        for (i=0;i<32;i=i+1) register[i] <= 31'b0;
        register[0] <= 32'b00000000000000000000000000000000;
        register[1] <= 32'b00000000000000000000000000000000;
        register[2] <= 32'b00000000000000000000000000000000;
    
        reg_wb_data = 0;
        reg_wb_wen = 0;

        pc = 0;
        reg_inst = 0;
        reg_iaddr = 0;
        reg_raddr = 0;
        reg_wdata = 0;
        reg_wen = 0;
        alu_out = 0;
        stage = ST_IF;
    end

    always @(posedge clock) begin
        case (stage)
            ST_IF: begin
                reg_tx_start <= 1;
                reg_tx_data <= rdata[31:24];
                REGISTER_TEST <= register[4][31:0];
                reg_inst <= inst;
                pc_p4 <= pc + 4;

                stage <= ST_ID;
            end

            ST_ID: begin
                opcode = reg_inst[0+:7];
                rd = reg_inst[7+:5];
                funct3 = reg_inst[12+:3];
                rs1 <= reg_inst[19:15];
                rs2 <= reg_inst[24:20];
                funct7 = reg_inst[25+:7];

                i_imm <= reg_inst[20+:12];
                s_imm <= { reg_inst[31:25], reg_inst[11:7] };
                b_imm = { reg_inst[25+:7], reg_inst[7+:5] };
                u_imm[31:12] = reg_inst[31:12];
                j_imm = {{12{reg_inst[31]}}, reg_inst[19:12], reg_inst[20], reg_inst[30:25], reg_inst[24:21], 1'b0};

                stage <= ST_EX;
            end

            ST_EX: begin
                if ((reg_inst & `MASK_OP_SW) == `OP_SW)
                    alu_out = rs1_data + s_imm_sext;
                if ((reg_inst & `MASK_OP_LW) == `OP_LW)
                    alu_out = rs1_data + i_imm_sext;
                if ((reg_inst & `MASK_OP_LUI) == `OP_LUI) begin
                    reg_wb_data[31:12] = u_imm[31:12];
                    reg_wb_wen = 1;
                end
                if ((reg_inst & `MASK_OP_ADDI) == `OP_ADDI) begin
                    reg_wb_data = rs1_data + i_imm_sext;
                    reg_wb_wen = 1;
                end

                stage <= ST_ACCESS;
            end

            ST_ACCESS: begin
                reg_raddr = alu_out;
                reg_wen = opcode == `OP_SW;
                reg_wdata = rs2_data;

                stage <= ST_WB;
            end

            ST_WB: begin

                if (opcode == `OP_LW)
                    register[rd] <= rdata;
                if (reg_wb_wen == 1)
                    register[rd] <= reg_wb_data;

                reg_wb_wen = 0;
                pc = pc_p4;
                alu_out = 0;
                reg_wen = 0;
                reg_iaddr = pc_p4;

                stage <= ST_IF;
            end
        endcase
    end

    assign rs1_data = register[rs1];
    assign rs2_data = register[rs2];

    assign i_imm_sext = { {20{i_imm[11]}}, i_imm[10:0] };
    assign s_imm_sext = { {20{s_imm[11]}}, s_imm[10:0] };

    assign tx_start = reg_tx_start;
    assign tx_data = reg_tx_data;

    assign iaddr = reg_iaddr;
    assign raddr = reg_raddr;
    assign wdata = reg_wdata;
    assign wen = reg_wen;

endmodule

src/memory.v
module MEMORY(
    input clock,

    input [31:0] raddr,
    input [31:0] iaddr,
    input wen,
    input [31:0] wdata,
    
    output [31:0] inst,
    output [31:0] rdata
);

    reg [7:0] mem [32:0];
    
    reg [31:0] reg_raddr;
    
    integer i;
    initial begin
        for (i=0;i<64;i=i+1) mem[i] <= 0;

        mem[0] <= 8'b1101_1101;
        mem[1] <= 8'b0000_0000;
        mem[2] <= 8'b0000_0010;
        mem[3] <= 8'b0011_0111;

        mem[4] <= 8'b0000_0011;
        mem[5] <= 8'b0011_0010;
        mem[6] <= 8'b0000_0010;
        mem[7] <= 8'b0001_0011;

        reg_raddr <= 32'b0;
    end

    always @(posedge clock) begin
        if (wen == 1'b1) begin
            mem[raddr] = wdata[0 +:8];
            mem[raddr+1] = wdata[8 +:8];
            mem[raddr+2] = wdata[16 +:8];
            mem[raddr+3] = wdata[24 +:8];
        end
    end

    assign inst = {
        mem[iaddr+0],
        mem[iaddr+1],
        mem[iaddr+2],
        mem[iaddr+3]
    };

    assign rdata = {
        mem[raddr+0],
        mem[raddr+1],
        mem[raddr+2],
        mem[raddr+3]
    };

endmodule

src/uart.v
module UART(
    input clock,

    input [7:0] data_in,
    input start,

    output tx_busy,
    output tx,
    output LED
);

    // UART Clock
    localparam FPGA_FREQ = 27; // MHz
    localparam UART_FREQ = 115200;
    localparam TX_CLOCK_COUNT_MAX = FPGA_FREQ * 1000000 / UART_FREQ - 1;

    reg [31:0] clock_count;

    reg led_flag;
    assign LED = led_flag;

    wire tx_clock = (clock_count == 0);

    initial begin
        clock_count = 0;
    end

    always @(posedge clock) begin
        if (clock_count == TX_CLOCK_COUNT_MAX) begin
            clock_count <= 0;
            led_flag <= ~led_flag;
        end else begin
            clock_count <= clock_count + 1;
        end
    end


    // State Machine
    localparam S_IDLE = 0;
    localparam S_START = 1;
    localparam S_SEND = 2;
    localparam S_P = 3;
    localparam S_END = 4;

    reg [4:0] state;
    reg [3:0] send_count;

    reg tx_reg;
    reg [7:0] data;
    reg [7:0] local_in;
    reg local_start;

    assign tx = tx_reg;

    always @(posedge clock) begin
        local_in <= data_in;
        local_start <= start;
    end

    assign tx_busy = (state != S_IDLE);

    initial begin
        state = S_IDLE;
        send_count = 0;
        tx_reg = 1'b1;
    end

    always @(posedge clock) begin
        case (state)
            S_IDLE:
                if (tx_clock) begin
                    if (local_start) begin
                        tx_reg <= 1'b1;
                        state <= S_START;
                    end else begin
                        tx_reg <= 1'b1;
                        state <= S_IDLE;
                    end
                end

            S_START: 
                if (tx_clock) begin
                    tx_reg <= 1'b0;
                    data <= local_in;
                    send_count <= 0;
                    state <= S_SEND;
                end else begin
                    tx_reg <= 1'b0;
                    state <= S_START;
                end

            S_SEND:
                if (tx_clock) begin
                    tx_reg <= data[send_count];
                    if (send_count == 3'd7) begin
                        state <= S_P;
                    end else begin
                        send_count <= send_count + 1;
                        state <= S_SEND;
                    end
                end else begin
                    tx_reg <= data[send_count];
                    state <= S_SEND;
                end

            S_P:
                if (tx_clock) begin
                    tx_reg <= 1'b1;
                    state <= S_END;
                end else begin
                    tx_reg <= 1'b1;
                    state <= S_P;
                end

            S_END:
                if (tx_clock) begin
                    tx_reg <= 1'b1;
                    state <= S_IDLE;
                end else begin
                    tx_reg <= 1'b1;
                    state <= S_END;
                end
        endcase
    end

endmodule

src/top.v
module TOP(
    input clock,
    output LED,
    output tx
);

    wire tx_busy;
    wire tx_start;
    wire [7:0] tx_data;

    UART uart0(
        .clock(clock),
        .tx(tx),
        .tx_busy(tx_busy),
        .start(tx_start),
        .data_in(tx_data),
        .LED(LED)
    );

    wire [31:0] inst;
    wire [31:0] rdata;
    wire [31:0] raddr;
    wire [31:0] iaddr;
    wire [31:0] wdata;
    wire wen;
    MEMORY mem0(
        .clock(clock),
        .raddr(raddr),
        .iaddr(iaddr),
        .wen(wen),
        .wdata(wdata),
        .inst(inst),
        .rdata(rdata)
    );

    CORE core0(
        .clock(clock),
        .tx_start(tx_start),
        .tx_data(tx_data),
        .raddr(raddr),
        .iaddr(iaddr),
        .wen(wen),
        .wdata(wdata),
        .inst(inst),
        .rdata(rdata)
    );
/*
    localparam MEM_WRITE = 0;
    localparam MEM_READ = 1;
    localparam MEM_IDLE = 2;

    localparam WAIT_TIME = 200000;
    reg [31:0] clock_count;
    reg [7:0] send_count;
    reg [3:0] state;
    wire [4 * 8:0] str = "test";
    initial begin
        clock_count = WAIT_TIME;
        send_count = 0;
        state = MEM_WRITE;
        tx_start = 1'b0;
        tx_data = 8'b0;
    end

    always @(posedge clock) begin
        if (clock_count == WAIT_TIME) begin

            case (state)
                MEM_WRITE: begin
                    raddr <= 32'b0;
                    wdata <= "C";
                    wen <= 1'b1;
                    state <= MEM_READ;
                end

                MEM_READ: begin
                    wen <= 1'b0;
                    raddr <= 32'b0;
                    if (tx_busy == 1'b0) begin
                        tx_data <= rdata[0 +:8];
                        tx_start <= 1'b1;
                    end
                    state <= MEM_IDLE;
                end

                MEM_IDLE:
                    state <= MEM_WRITE;
            endcase

            clock_count <= 0;
        end else begin
            clock_count <= clock_count + 1;
            tx_start <= 1'b1;
        end
    end*/

endmodule

src/uart_tb.v
module memory_tb;

    parameter RATE = 1;

    initial begin
        $dumpfile("tb_memory.vcd");
        $dumpvars(3, memory_tb);

        # (10000) $finish;
    end

    reg clk = 0;
    always #(RATE) clk = !clk;
    wire LED;
    wire TX;

    TOP top(
        .clock(clk),
        .LED(LED),
        .tx(TX)
    );

endmodule

src/tb_memory.vcd
$date
	Thu May 18 16:48:10 2023
$end
$version
	Icarus Verilog
$end
$timescale
	1s
$end
$scope module memory_tb $end
$var wire 1 ! TX $end
$var wire 1 " LED $end
$var parameter 32 # RATE $end
$var reg 1 $ clk $end
$scope module top $end
$var wire 1 $ clock $end
$var wire 1 % wen $end
$var wire 32 & wdata [31:0] $end
$var wire 1 ' tx_start $end
$var wire 8 ( tx_data [7:0] $end
$var wire 1 ) tx_busy $end
$var wire 1 ! tx $end
$var wire 32 * rdata [31:0] $end
$var wire 32 + raddr [31:0] $end
$var wire 32 , inst [31:0] $end
$var wire 32 - iaddr [31:0] $end
$var wire 1 " LED $end
$scope module core0 $end
$var wire 1 $ clock $end
$var wire 32 . rs1_data [31:0] $end
$var wire 32 / rs2_data [31:0] $end
$var wire 8 0 tx_data [7:0] $end
$var wire 1 ' tx_start $end
$var wire 32 1 wdata [31:0] $end
$var wire 1 % wen $end
$var wire 32 2 s_imm_sext [31:0] $end
$var wire 32 3 rdata [31:0] $end
$var wire 32 4 raddr [31:0] $end
$var wire 32 5 inst [31:0] $end
$var wire 32 6 iaddr [31:0] $end
$var wire 32 7 i_imm_sext [31:0] $end
$var parameter 32 8 ST_ACCESS $end
$var parameter 32 9 ST_EX $end
$var parameter 32 : ST_ID $end
$var parameter 32 ; ST_IF $end
$var parameter 32 < ST_WB $end
$var reg 32 = REGISTER_TEST [31:0] $end
$var reg 32 > alu_out [31:0] $end
$var reg 13 ? b_imm [12:0] $end
$var reg 3 @ funct3 [2:0] $end
$var reg 7 A funct7 [6:0] $end
$var reg 12 B i_imm [11:0] $end
$var reg 21 C j_imm [20:0] $end
$var reg 7 D opcode [6:0] $end
$var reg 32 E pc [31:0] $end
$var reg 32 F pc_p4 [31:0] $end
$var reg 5 G rd [4:0] $end
$var reg 32 H reg_iaddr [31:0] $end
$var reg 32 I reg_inst [31:0] $end
$var reg 32 J reg_raddr [31:0] $end
$var reg 8 K reg_tx_data [7:0] $end
$var reg 1 L reg_tx_start $end
$var reg 32 M reg_wb_data [31:0] $end
$var reg 1 N reg_wb_wen $end
$var reg 32 O reg_wdata [31:0] $end
$var reg 1 P reg_wen $end
$var reg 5 Q rs1 [4:0] $end
$var reg 5 R rs2 [4:0] $end
$var reg 12 S s_imm [11:0] $end
$var reg 4 T stage [3:0] $end
$var reg 32 U u_imm [31:0] $end
$var integer 32 V i [31:0] $end
$upscope $end
$scope module mem0 $end
$var wire 1 $ clock $end
$var wire 32 W iaddr [31:0] $end
$var wire 32 X raddr [31:0] $end
$var wire 32 Y wdata [31:0] $end
$var wire 1 % wen $end
$var wire 32 Z rdata [31:0] $end
$var wire 32 [ inst [31:0] $end
$var reg 32 \ reg_raddr [31:0] $end
$var integer 32 ] i [31:0] $end
$upscope $end
$scope module uart0 $end
$var wire 1 " LED $end
$var wire 1 $ clock $end
$var wire 8 ^ data_in [7:0] $end
$var wire 1 ' start $end
$var wire 1 ! tx $end
$var wire 1 _ tx_clock $end
$var wire 1 ) tx_busy $end
$var parameter 32 ` FPGA_FREQ $end
$var parameter 32 a S_END $end
$var parameter 32 b S_IDLE $end
$var parameter 32 c S_P $end
$var parameter 32 d S_SEND $end
$var parameter 32 e S_START $end
$var parameter 65 f TX_CLOCK_COUNT_MAX $end
$var parameter 32 g UART_FREQ $end
$var reg 32 h clock_count [31:0] $end
$var reg 8 i data [7:0] $end
$var reg 1 j led_flag $end
$var reg 8 k local_in [7:0] $end
$var reg 1 l local_start $end
$var reg 4 m send_count [3:0] $end
$var reg 5 n state [4:0] $end
$var reg 1 o tx_reg $end
$upscope $end
$upscope $end
$upscope $end
$enddefinitions $end
$comment Show the parameter values. $end
$dumpall
b11100001000000000 g
b11101001 f
b1 e
b10 d
b11 c
b0 b
b100 a
b11011 `
b100 <
b0 ;
b1 :
b10 9
b11 8
b1 #
$end
#0
$dumpvars
1o
b0 n
b0 m
xl
bx k
xj
bx i
b0 h
1_
bx ^
b1000000 ]
b0 \
b11011101000000000000001000110111 [
b11011101000000000000001000110111 Z
b0 Y
b0 X
b0 W
b100000 V
bx U
b0 T
bx S
bx R
bx Q
0P
b0 O
0N
b0 M
xL
bx K
b0 J
b0 I
b0 H
bx G
bx F
b0 E
bx D
bx C
bx B
bx A
bx @
bx ?
b0 >
bx =
b0xxxxxxxxxxxxxxxxxxxxxxxxxxxxxxx 7
b0 6
b11011101000000000000001000110111 5
b0 4
b11011101000000000000001000110111 3
b0xxxxxxxxxxxxxxxxxxxxxxxxxxxxxxx 2
b0 1
bx 0
bx /
bx .
b0 -
b11011101000000000000001000110111 ,
b0 +
b11011101000000000000001000110111 *
0)
bx (
x'
b0 &
0%
0$
x"
1!
$end
#1
0_
b1 h
b1 T
b100 F
b11011101000000000000001000110111 I
b0 =
b11011101 (
b11011101 0
b11011101 ^
b11011101 K
1'
1L
1$
#2
0$
#3
b1111111111111111111110111000100 2
b1111111111111111111110111010000 7
b10 T
b110111000100 S
b110111010000 B
b0 /
b10000 R
b0 .
b0 Q
1l
b11011101 k
b10 h
b100000000010111010000 C
b11011101000000000000xxxxxxxxxxxx U
b110111000100 ?
b1101110 A
b0 @
b100 G
b110111 D
1$
#4
0$
#5
b11 h
b11 T
1N
b11011101000000000000000000000000 M
1$
#6
0$
#7
b100 T
b100 h
1$
#8
0$
#9
b101 h
b0 T
b11001100100000001000010011 ,
b11001100100000001000010011 5
b11001100100000001000010011 [
b100 -
b100 6
b100 H
b100 W
b100 E
0N
1$
#10
0$
#11
b1 T
b1000 F
b11001100100000001000010011 I
b11011101000000000000000000000000 =
b110 h
1$
#12
0$
#13
b100100 2
b110011 7
b111 h
b10 T
b100100 S
b110011 B
b10011 R
b11011101000000000000000000000000 .
b100 Q
b100000100000110010 C
b11001100100000xxxxxxxxxxxx U
b100100 ?
b1 A
b10011 D
1$
#14
0$
#15
b11 T
b1000 h
1N
b11011101000000000000000000110011 M
1$
#16
0$
#17
b1001 h
b100 T
1$
#18
0$
#19
b0 T
b11011101000000000000000000110011 .
b1010 h
b0 ,
b0 5
b0 [
b1000 -
b1000 6
b1000 H
b1000 W
b1000 E
0N
1$
#20
0$
#21
b1011 h
b1 T
b1100 F
b0 I
b11011101000000000000000000110011 =
1$
#22
0$
#23
b0 2
b0 7
b10 T
b0 S
b0 B
b0 R
b0 .
b0 Q
b1100 h
b0 C
b0xxxxxxxxxxxx U
b0 ?
b0 A
b0 G
b0 D
1$
#24
0$
#25
b1101 h
b11 T
1$
#26
0$
#27
b100 T
b1110 h
1$
#28
0$
#29
b1111 h
b0 T
b1100 -
b1100 6
b1100 H
b1100 W
b1100 E
1$
#30
0$
#31
b1 T
b10000 F
b10000 h
1$
#32
0$
#33
b10001 h
b10 T
1$
#34
0$
#35
b11 T
b10010 h
1$
#36
0$
#37
b10011 h
b100 T
1$
#38
0$
#39
b0 T
b10100 h
b10000 -
b10000 6
b10000 H
b10000 W
b10000 E
1$
#40
0$
#41
b10101 h
b1 T
b10100 F
1$
#42
0$
#43
b10 T
b10110 h
1$
#44
0$
#45
b10111 h
b11 T
1$
#46
0$
#47
b100 T
b11000 h
1$
#48
0$
#49
b11001 h
b0 T
b10100 -
b10100 6
b10100 H
b10100 W
b10100 E
1$
#50
0$
#51
b1 T
b11000 F
b11010 h
1$
#52
0$
#53
b11011 h
b10 T
1$
#54
0$
#55
b11 T
b11100 h
1$
#56
0$
#57
b11101 h
b100 T
1$
#58
0$
#59
b0 T
b11110 h
b11000 -
b11000 6
b11000 H
b11000 W
b11000 E
1$
#60
0$
#61
b11111 h
b1 T
b11100 F
1$
#62
0$
#63
b10 T
b100000 h
1$
#64
0$
#65
b100001 h
b11 T
1$
#66
0$
#67
b100 T
b100010 h
1$
#68
0$
#69
b100011 h
b0 T
b11100 -
b11100 6
b11100 H
b11100 W
b11100 E
1$
#70
0$
#71
b1 T
b100000 F
b100100 h
1$
#72
0$
#73
b100101 h
b10 T
1$
#74
0$
#75
b11 T
b100110 h
1$
#76
0$
#77
b100111 h
b100 T
1$
#78
0$
#79
b0 T
b101000 h
b0xxxxxxxxxxxxxxxxxxxxxxxx ,
b0xxxxxxxxxxxxxxxxxxxxxxxx 5
b0xxxxxxxxxxxxxxxxxxxxxxxx [
b100000 -
b100000 6
b100000 H
b100000 W
b100000 E
1$
#80
0$
#81
b101001 h
b1 T
b100100 F
b0xxxxxxxxxxxxxxxxxxxxxxxx I
1$
#82
0$
#83
b0xxxxx 2
b0xxxx 7
b10 T
b0xxxxx S
b0xxxx B
bx /
b0xxxx R
bx .
bx Q
b101010 h
b0xxxxxxxxx0000000xxx0 C
b0xxxxxxxxxxxxxxxxxxxxxxxx U
b0xxxxx ?
bx @
bx G
bx D
1$
#84
0$
#85
b101011 h
b11 T
1$
#86
0$
#87
b100 T
b101100 h
bx &
bx 1
bx Y
bx O
1$
#88
0$
#89
b101101 h
b0 T
bx ,
bx 5
bx [
b100100 -
b100100 6
b100100 H
b100100 W
b100100 E
1$
#90
0$
#91
b1 T
b101000 F
bx I
b101110 h
1$
#92
0$
#93
b0xxxxxxxxxxxxxxxxxxxxxxxxxxxxxxx 2
b0xxxxxxxxxxxxxxxxxxxxxxxxxxxxxxx 7
b101111 h
b10 T
bx S
bx B
bx R
bx0 C
bx U
b0xxxxxxxxxxxx ?
bx A
1$
#94
0$
#95
b11 T
b110000 h
1$
#96
0$
#97
b110001 h
b100 T
1$
#98
0$
#99
b0 T
b110010 h
b101000 -
b101000 6
b101000 H
b101000 W
b101000 E
1$
#100
0$
#101
b110011 h
b1 T
b101100 F
1$
#102
0$
#103
b10 T
b110100 h
1$
#104
0$
#105
b110101 h
b11 T
1$
#106
0$
#107
b100 T
b110110 h
1$
#108
0$
#109
b110111 h
b0 T
b101100 -
b101100 6
b101100 H
b101100 W
b101100 E
1$
#110
0$
#111
b1 T
b110000 F
b111000 h
1$
#112
0$
#113
b111001 h
b10 T
1$
#114
0$
#115
b11 T
b111010 h
1$
#116
0$
#117
b111011 h
b100 T
1$
#118
0$
#119
b0 T
b111100 h
b110000 -
b110000 6
b110000 H
b110000 W
b110000 E
1$
#120
0$
#121
b111101 h
b1 T
b110100 F
1$
#122
0$
#123
b10 T
b111110 h
1$
#124
0$
#125
b111111 h
b11 T
1$
#126
0$
#127
b100 T
b1000000 h
1$
#128
0$
#129
b1000001 h
b0 T
b110100 -
b110100 6
b110100 H
b110100 W
b110100 E
1$
#130
0$
#131
b1 T
b111000 F
b1000010 h
1$
#132
0$
#133
b1000011 h
b10 T
1$
#134
0$
#135
b11 T
b1000100 h
1$
#136
0$
#137
b1000101 h
b100 T
1$
#138
0$
#139
b0 T
b1000110 h
b111000 -
b111000 6
b111000 H
b111000 W
b111000 E
1$
#140
0$
#141
b1000111 h
b1 T
b111100 F
1$
#142
0$
#143
b10 T
b1001000 h
1$
#144
0$
#145
b1001001 h
b11 T
1$
#146
0$
#147
b100 T
b1001010 h
1$
#148
0$
#149
b1001011 h
b0 T
b111100 -
b111100 6
b111100 H
b111100 W
b111100 E
1$
#150
0$
#151
b1 T
b1000000 F
b1001100 h
1$
#152
0$
#153
b1001101 h
b10 T
1$
#154
0$
#155
b11 T
b1001110 h
1$
#156
0$
#157
b1001111 h
b100 T
1$
#158
0$
#159
b0 T
b1010000 h
b1000000 -
b1000000 6
b1000000 H
b1000000 W
b1000000 E
1$
#160
0$
#161
b1010001 h
b1 T
b1000100 F
1$
#162
0$
#163
b10 T
b1010010 h
1$
#164
0$
#165
b1010011 h
b11 T
1$
#166
0$
#167
b100 T
b1010100 h
1$
#168
0$
#169
b1010101 h
b0 T
b1000100 -
b1000100 6
b1000100 H
b1000100 W
b1000100 E
1$
#170
0$
#171
b1 T
b1001000 F
b1010110 h
1$
#172
0$
#173
b1010111 h
b10 T
1$
#174
0$
#175
b11 T
b1011000 h
1$
#176
0$
#177
b1011001 h
b100 T
1$
#178
0$
#179
b0 T
b1011010 h
b1001000 -
b1001000 6
b1001000 H
b1001000 W
b1001000 E
1$
#180
0$
#181
b1011011 h
b1 T
b1001100 F
1$
#182
0$
#183
b10 T
b1011100 h
1$
#184
0$
#185
b1011101 h
b11 T
1$
#186
0$
#187
b100 T
b1011110 h
1$
#188
0$
#189
b1011111 h
b0 T
b1001100 -
b1001100 6
b1001100 H
b1001100 W
b1001100 E
1$
#190
0$
#191
b1 T
b1010000 F
b1100000 h
1$
#192
0$
#193
b1100001 h
b10 T
1$
#194
0$
#195
b11 T
b1100010 h
1$
#196
0$
#197
b1100011 h
b100 T
1$
#198
0$
#199
b0 T
b1100100 h
b1010000 -
b1010000 6
b1010000 H
b1010000 W
b1010000 E
1$
#200
0$
#201
b1100101 h
b1 T
b1010100 F
1$
#202
0$
#203
b10 T
b1100110 h
1$
#204
0$
#205
b1100111 h
b11 T
1$
#206
0$
#207
b100 T
b1101000 h
1$
#208
0$
#209
b1101001 h
b0 T
b1010100 -
b1010100 6
b1010100 H
b1010100 W
b1010100 E
1$
#210
0$
#211
b1 T
b1011000 F
b1101010 h
1$
#212
0$
#213
b1101011 h
b10 T
1$
#214
0$
#215
b11 T
b1101100 h
1$
#216
0$
#217
b1101101 h
b100 T
1$
#218
0$
#219
b0 T
b1101110 h
b1011000 -
b1011000 6
b1011000 H
b1011000 W
b1011000 E
1$
#220
0$
#221
b1101111 h
b1 T
b1011100 F
1$
#222
0$
#223
b10 T
b1110000 h
1$
#224
0$
#225
b1110001 h
b11 T
1$
#226
0$
#227
b100 T
b1110010 h
1$
#228
0$
#229
b1110011 h
b0 T
b1011100 -
b1011100 6
b1011100 H
b1011100 W
b1011100 E
1$
#230
0$
#231
b1 T
b1100000 F
b1110100 h
1$
#232
0$
#233
b1110101 h
b10 T
1$
#234
0$
#235
b11 T
b1110110 h
1$
#236
0$
#237
b1110111 h
b100 T
1$
#238
0$
#239
b0 T
b1111000 h
b1100000 -
b1100000 6
b1100000 H
b1100000 W
b1100000 E
1$
#240
0$
#241
b1111001 h
b1 T
b1100100 F
1$
#242
0$
#243
b10 T
b1111010 h
1$
#244
0$
#245
b1111011 h
b11 T
1$
#246
0$
#247
b100 T
b1111100 h
1$
#248
0$
#249
b1111101 h
b0 T
b1100100 -
b1100100 6
b1100100 H
b1100100 W
b1100100 E
1$
#250
0$
#251
b1 T
b1101000 F
b1111110 h
1$
#252
0$
#253
b1111111 h
b10 T
1$
#254
0$
#255
b11 T
b10000000 h
1$
#256
0$
#257
b10000001 h
b100 T
1$
#258
0$
#259
b0 T
b10000010 h
b1101000 -
b1101000 6
b1101000 H
b1101000 W
b1101000 E
1$
#260
0$
#261
b10000011 h
b1 T
b1101100 F
1$
#262
0$
#263
b10 T
b10000100 h
1$
#264
0$
#265
b10000101 h
b11 T
1$
#266
0$
#267
b100 T
b10000110 h
1$
#268
0$
#269
b10000111 h
b0 T
b1101100 -
b1101100 6
b1101100 H
b1101100 W
b1101100 E
1$
#270
0$
#271
b1 T
b1110000 F
b10001000 h
1$
#272
0$
#273
b10001001 h
b10 T
1$
#274
0$
#275
b11 T
b10001010 h
1$
#276
0$
#277
b10001011 h
b100 T
1$
#278
0$
#279
b0 T
b10001100 h
b1110000 -
b1110000 6
b1110000 H
b1110000 W
b1110000 E
1$
#280
0$
#281
b10001101 h
b1 T
b1110100 F
1$
#282
0$
#283
b10 T
b10001110 h
1$
#284
0$
#285
b10001111 h
b11 T
1$
#286
0$
#287
b100 T
b10010000 h
1$
#288
0$
#289
b10010001 h
b0 T
b1110100 -
b1110100 6
b1110100 H
b1110100 W
b1110100 E
1$
#290
0$
#291
b1 T
b1111000 F
b10010010 h
1$
#292
0$
#293
b10010011 h
b10 T
1$
#294
0$
#295
b11 T
b10010100 h
1$
#296
0$
#297
b10010101 h
b100 T
1$
#298
0$
#299
b0 T
b10010110 h
b1111000 -
b1111000 6
b1111000 H
b1111000 W
b1111000 E
1$
#300
0$
#301
b10010111 h
b1 T
b1111100 F
1$
#302
0$
#303
b10 T
b10011000 h
1$
#304
0$
#305
b10011001 h
b11 T
1$
#306
0$
#307
b100 T
b10011010 h
1$
#308
0$
#309
b10011011 h
b0 T
b1111100 -
b1111100 6
b1111100 H
b1111100 W
b1111100 E
1$
#310
0$
#311
b1 T
b10000000 F
b10011100 h
1$
#312
0$
#313
b10011101 h
b10 T
1$
#314
0$
#315
b11 T
b10011110 h
1$
#316
0$
#317
b10011111 h
b100 T
1$
#318
0$
#319
b0 T
b10100000 h
b10000000 -
b10000000 6
b10000000 H
b10000000 W
b10000000 E
1$
#320
0$
#321
b10100001 h
b1 T
b10000100 F
1$
#322
0$
#323
b10 T
b10100010 h
1$
#324
0$
#325
b10100011 h
b11 T
1$
#326
0$
#327
b100 T
b10100100 h
1$
#328
0$
#329
b10100101 h
b0 T
b10000100 -
b10000100 6
b10000100 H
b10000100 W
b10000100 E
1$
#330
0$
#331
b1 T
b10001000 F
b10100110 h
1$
#332
0$
#333
b10100111 h
b10 T
1$
#334
0$
#335
b11 T
b10101000 h
1$
#336
0$
#337
b10101001 h
b100 T
1$
#338
0$
#339
b0 T
b10101010 h
b10001000 -
b10001000 6
b10001000 H
b10001000 W
b10001000 E
1$
#340
0$
#341
b10101011 h
b1 T
b10001100 F
1$
#342
0$
#343
b10 T
b10101100 h
1$
#344
0$
#345
b10101101 h
b11 T
1$
#346
0$
#347
b100 T
b10101110 h
1$
#348
0$
#349
b10101111 h
b0 T
b10001100 -
b10001100 6
b10001100 H
b10001100 W
b10001100 E
1$
#350
0$
#351
b1 T
b10010000 F
b10110000 h
1$
#352
0$
#353
b10110001 h
b10 T
1$
#354
0$
#355
b11 T
b10110010 h
1$
#356
0$
#357
b10110011 h
b100 T
1$
#358
0$
#359
b0 T
b10110100 h
b10010000 -
b10010000 6
b10010000 H
b10010000 W
b10010000 E
1$
#360
0$
#361
b10110101 h
b1 T
b10010100 F
1$
#362
0$
#363
b10 T
b10110110 h
1$
#364
0$
#365
b10110111 h
b11 T
1$
#366
0$
#367
b100 T
b10111000 h
1$
#368
0$
#369
b10111001 h
b0 T
b10010100 -
b10010100 6
b10010100 H
b10010100 W
b10010100 E
1$
#370
0$
#371
b1 T
b10011000 F
b10111010 h
1$
#372
0$
#373
b10111011 h
b10 T
1$
#374
0$
#375
b11 T
b10111100 h
1$
#376
0$
#377
b10111101 h
b100 T
1$
#378
0$
#379
b0 T
b10111110 h
b10011000 -
b10011000 6
b10011000 H
b10011000 W
b10011000 E
1$
#380
0$
#381
b10111111 h
b1 T
b10011100 F
1$
#382
0$
#383
b10 T
b11000000 h
1$
#384
0$
#385
b11000001 h
b11 T
1$
#386
0$
#387
b100 T
b11000010 h
1$
#388
0$
#389
b11000011 h
b0 T
b10011100 -
b10011100 6
b10011100 H
b10011100 W
b10011100 E
1$
#390
0$
#391
b1 T
b10100000 F
b11000100 h
1$
#392
0$
#393
b11000101 h
b10 T
1$
#394
0$
#395
b11 T
b11000110 h
1$
#396
0$
#397
b11000111 h
b100 T
1$
#398
0$
#399
b0 T
b11001000 h
b10100000 -
b10100000 6
b10100000 H
b10100000 W
b10100000 E
1$
#400
0$
#401
b11001001 h
b1 T
b10100100 F
1$
#402
0$
#403
b10 T
b11001010 h
1$
#404
0$
#405
b11001011 h
b11 T
1$
#406
0$
#407
b100 T
b11001100 h
1$
#408
0$
#409
b11001101 h
b0 T
b10100100 -
b10100100 6
b10100100 H
b10100100 W
b10100100 E
1$
#410
0$
#411
b1 T
b10101000 F
b11001110 h
1$
#412
0$
#413
b11001111 h
b10 T
1$
#414
0$
#415
b11 T
b11010000 h
1$
#416
0$
#417
b11010001 h
b100 T
1$
#418
0$
#419
b0 T
b11010010 h
b10101000 -
b10101000 6
b10101000 H
b10101000 W
b10101000 E
1$
#420
0$
#421
b11010011 h
b1 T
b10101100 F
1$
#422
0$
#423
b10 T
b11010100 h
1$
