src/defs.vh
`define OP_SW 7'b0100011
`define OP_LW 7'b0000011

src/core.v
`include "defs.vh"

module CORE(
    input clock,

// UART
    output tx_start,
    output [7:0] tx_data,

// Memory
    output [31:0] raddr,
    output [31:0] iaddr,
    output wen,
    output [31:0] wdata,
    input [31:0] inst,
    input [31:0] rdata
);

    reg [31:0] register [31:0];
    reg [31:0] REGISTER_TEST;

    reg [7:0] reg_tx_data;
    reg reg_tx_start;

    reg [31:0] pc;
    reg [31:0] pc_p4;
    reg [31:0] reg_inst;
    reg [31:0] reg_iaddr;
    reg [31:0] reg_raddr;
    reg [31:0] reg_wdata;
    reg reg_wen;

    reg [6:0] opcode;
    reg [4:0] rd;
    reg [2:0] funct3;
    reg [4:0] rs1;
    reg [4:0] rs2;
    reg [6:0] funct7;

    wire [31:0] rs1_data;
    wire [31:0] rs2_data;

    reg [11:0] i_imm;
    wire [31:0] i_imm_sext;
    reg [11:0] s_imm;
    wire [31:0] s_imm_sext;
    reg [12:0] b_imm;
    reg [31:0] u_imm;
    reg [20:0] j_imm;

    reg [31:0] alu_out;

    localparam ST_IF = 0;
    localparam ST_ID = 1;
    localparam ST_EX = 2;
    localparam ST_ACCESS = 3;
    localparam ST_WB = 4;
    reg [3:0] stage;

    integer i;
    initial begin
        for (i=0;i<32;i=i+1) register[i] <= 31'b0;
        register[0] <= 32'b00000000000000000000000000000000;
        register[1] <= 32'b00000000000000000000000000000000;
        register[2] <= 32'b00000000000000000000000001000001;

        pc = 0;
        reg_inst = 0;
        reg_iaddr = 0;
        reg_raddr = 0;
        reg_wdata = 0;
        reg_wen = 0;
        alu_out = 0;
        stage = ST_IF;
    end

    always @(posedge clock) begin
        case (stage)
            ST_IF: begin
                reg_tx_start <= 1;
                reg_tx_data <= rdata[31:24];
                REGISTER_TEST <= register[1][31:0];
                reg_inst <= inst;
                pc_p4 <= pc + 4;

                stage <= ST_ID;
            end

            ST_ID: begin
                opcode = reg_inst[0+:7];
                rd = reg_inst[7+:5];
                funct3 = reg_inst[12+:3];
                rs1 <= reg_inst[19:15];
                rs2 <= reg_inst[24:20];
                funct7 = reg_inst[25+:7];

                i_imm <= reg_inst[20+:12];
                s_imm <= { reg_inst[31:25], reg_inst[11:7] };
                b_imm = { reg_inst[25+:7], reg_inst[7+:5] };
                u_imm[31:12] = reg_inst[31:12];
                j_imm = {{12{reg_inst[31]}}, reg_inst[19:12], reg_inst[20], reg_inst[30:25], reg_inst[24:21], 1'b0};

                stage <= ST_EX;
            end

            ST_EX: begin

                case (opcode)
                    `OP_SW:
                        alu_out = rs1_data + s_imm_sext;
                    `OP_LW:
                        alu_out = rs1_data + i_imm_sext;
                endcase

                stage <= ST_ACCESS;
            end

            ST_ACCESS: begin
                reg_raddr = alu_out;
                reg_wen = opcode == `OP_SW;
                reg_wdata = rs2_data;

                stage <= ST_WB;
            end

            ST_WB: begin

                if (opcode == `OP_LW)
                    register[rd] <= rdata;

                pc = pc_p4;
                alu_out = 0;
                reg_wen = 0;
                reg_iaddr = pc_p4;

                stage <= ST_IF;
            end
        endcase
    end

    assign rs1_data = register[rs1];
    assign rs2_data = register[rs2];

    assign i_imm_sext = { {20{i_imm[11]}}, i_imm[10:0] };
    assign s_imm_sext = { {20{s_imm[11]}}, s_imm[10:0] };

    assign tx_start = reg_tx_start;
    assign tx_data = reg_tx_data;

    assign iaddr = reg_iaddr;
    assign raddr = reg_raddr;
    assign wdata = reg_wdata;
    assign wen = reg_wen;

endmodule

src/memory.v
module MEMORY(
    input clock,

    input [31:0] raddr,
    input [31:0] iaddr,
    input wen,
    input [31:0] wdata,
    
    output [31:0] inst,
    output [31:0] rdata
);

    reg [7:0] mem [32:0];
    
    reg [31:0] reg_raddr;
    
    integer i;
    initial begin
        for (i=0;i<64;i=i+1) mem[i] <= 0;
        mem[0] <= 8'b00000000;
        mem[1] <= 8'b00100000;
        mem[2] <= 8'b10100010;
        mem[3] <= 8'b00100011;

        mem[0] <= 8'b00000000;
        mem[1] <= 8'b00100000;
        mem[2] <= 8'b10100010;
        mem[3] <= 8'b00100011;
        reg_raddr <= 32'b0;
    end

    always @(posedge clock) begin
        if (wen == 1'b1) begin
            mem[raddr] = wdata[0 +:8];
            mem[raddr+1] = wdata[8 +:8];
            mem[raddr+2] = wdata[16 +:8];
            mem[raddr+3] = wdata[24 +:8];
        end
    end

    assign inst = {
        mem[iaddr+0],
        mem[iaddr+1],
        mem[iaddr+2],
        mem[iaddr+3]
    };

    assign rdata = {
        mem[raddr+0],
        mem[raddr+1],
        mem[raddr+2],
        mem[raddr+3]
    };

endmodule

src/uart.v
module UART(
    input clock,

    input [7:0] data_in,
    input start,

    output tx_busy,
    output tx,
    output LED
);

    // UART Clock
    localparam FPGA_FREQ = 27; // MHz
    localparam UART_FREQ = 115200;
    localparam TX_CLOCK_COUNT_MAX = FPGA_FREQ * 1000000 / UART_FREQ - 1;

    reg [31:0] clock_count;

    reg led_flag;
    assign LED = led_flag;

    wire tx_clock = (clock_count == 0);

    initial begin
        clock_count = 0;
    end

    always @(posedge clock) begin
        if (clock_count == TX_CLOCK_COUNT_MAX) begin
            clock_count <= 0;
            led_flag <= ~led_flag;
        end else begin
            clock_count <= clock_count + 1;
        end
    end


    // State Machine
    localparam S_IDLE = 0;
    localparam S_START = 1;
    localparam S_SEND = 2;
    localparam S_P = 3;
    localparam S_END = 4;

    reg [4:0] state;
    reg [3:0] send_count;

    reg tx_reg;
    reg [7:0] data;
    reg [7:0] local_in;
    reg local_start;

    assign tx = tx_reg;

    always @(posedge clock) begin
        local_in <= data_in;
        local_start <= start;
    end

    assign tx_busy = (state != S_IDLE);

    initial begin
        state = S_IDLE;
        send_count = 0;
        tx_reg = 1'b1;
    end

    always @(posedge clock) begin
        case (state)
            S_IDLE:
                if (tx_clock) begin
                    if (local_start) begin
                        tx_reg <= 1'b1;
                        state <= S_START;
                    end else begin
                        tx_reg <= 1'b1;
                        state <= S_IDLE;
                    end
                end

            S_START: 
                if (tx_clock) begin
                    tx_reg <= 1'b0;
                    data <= local_in;
                    send_count <= 0;
                    state <= S_SEND;
                end else begin
                    tx_reg <= 1'b0;
                    state <= S_START;
                end

            S_SEND:
                if (tx_clock) begin
                    tx_reg <= data[send_count];
                    if (send_count == 3'd7) begin
                        state <= S_P;
                    end else begin
                        send_count <= send_count + 1;
                        state <= S_SEND;
                    end
                end else begin
                    tx_reg <= data[send_count];
                    state <= S_SEND;
                end

            S_P:
                if (tx_clock) begin
                    tx_reg <= 1'b1;
                    state <= S_END;
                end else begin
                    tx_reg <= 1'b1;
                    state <= S_P;
                end

            S_END:
                if (tx_clock) begin
                    tx_reg <= 1'b1;
                    state <= S_IDLE;
                end else begin
                    tx_reg <= 1'b1;
                    state <= S_END;
                end
        endcase
    end

endmodule

src/top.v
module TOP(
    input clock,
    output LED,
    output tx
);

    wire tx_busy;
    wire tx_start;
    wire [7:0] tx_data;

    UART uart0(
        .clock(clock),
        .tx(tx),
        .tx_busy(tx_busy),
        .start(tx_start),
        .data_in(tx_data),
        .LED(LED)
    );

    wire [31:0] inst;
    wire [31:0] rdata;
    wire [31:0] raddr;
    wire [31:0] iaddr;
    wire [31:0] wdata;
    wire wen;
    MEMORY mem0(
        .clock(clock),
        .raddr(raddr),
        .iaddr(iaddr),
        .wen(wen),
        .wdata(wdata),
        .inst(inst),
        .rdata(rdata)
    );

    CORE core0(
        .clock(clock),
        .tx_start(tx_start),
        .tx_data(tx_data),
        .raddr(raddr),
        .iaddr(iaddr),
        .wen(wen),
        .wdata(wdata),
        .inst(inst),
        .rdata(rdata)
    );
/*
    localparam MEM_WRITE = 0;
    localparam MEM_READ = 1;
    localparam MEM_IDLE = 2;

    localparam WAIT_TIME = 200000;
    reg [31:0] clock_count;
    reg [7:0] send_count;
    reg [3:0] state;
    wire [4 * 8:0] str = "test";
    initial begin
        clock_count = WAIT_TIME;
        send_count = 0;
        state = MEM_WRITE;
        tx_start = 1'b0;
        tx_data = 8'b0;
    end

    always @(posedge clock) begin
        if (clock_count == WAIT_TIME) begin

            case (state)
                MEM_WRITE: begin
                    raddr <= 32'b0;
                    wdata <= "C";
                    wen <= 1'b1;
                    state <= MEM_READ;
                end

                MEM_READ: begin
                    wen <= 1'b0;
                    raddr <= 32'b0;
                    if (tx_busy == 1'b0) begin
                        tx_data <= rdata[0 +:8];
                        tx_start <= 1'b1;
                    end
                    state <= MEM_IDLE;
                end

                MEM_IDLE:
                    state <= MEM_WRITE;
            endcase

            clock_count <= 0;
        end else begin
            clock_count <= clock_count + 1;
            tx_start <= 1'b1;
        end
    end*/

endmodule

src/uart_tb.v
module memory_tb;

    parameter RATE = 1;

    initial begin
        $dumpfile("tb_memory.vcd");
        $dumpvars(3, memory_tb);

        # (10000) $finish;
    end

    reg clk = 0;
    always #(RATE) clk = !clk;
    wire LED;
    wire TX;

    TOP top(
        .clock(clk),
        .LED(LED),
        .tx(TX)
    );

endmodule

src/tb_memory.vcd
$date
	Thu May 18 13:59:51 2023
$end
$version
	Icarus Verilog
$end
$timescale
	1s
$end
$scope module memory_tb $end
$var wire 1 ! TX $end
$var wire 1 " LED $end
$var parameter 32 # RATE $end
$var reg 1 $ clk $end
$scope module top $end
$var wire 1 $ clock $end
$var wire 1 % wen $end
$var wire 32 & wdata [31:0] $end
$var wire 1 ' tx_start $end
$var wire 8 ( tx_data [7:0] $end
$var wire 1 ) tx_busy $end
$var wire 1 ! tx $end
$var wire 32 * rdata [31:0] $end
$var wire 32 + raddr [31:0] $end
$var wire 32 , inst [31:0] $end
$var wire 32 - iaddr [31:0] $end
$var wire 1 " LED $end
$scope module core0 $end
$var wire 1 $ clock $end
$var wire 32 . rs1_data [31:0] $end
$var wire 32 / rs2_data [31:0] $end
$var wire 8 0 tx_data [7:0] $end
$var wire 1 ' tx_start $end
$var wire 32 1 wdata [31:0] $end
$var wire 1 % wen $end
$var wire 32 2 s_imm_sext [31:0] $end
$var wire 32 3 rdata [31:0] $end
$var wire 32 4 raddr [31:0] $end
$var wire 32 5 inst [31:0] $end
$var wire 32 6 iaddr [31:0] $end
$var wire 32 7 i_imm_sext [31:0] $end
$var parameter 32 8 ST_ACCESS $end
$var parameter 32 9 ST_EX $end
$var parameter 32 : ST_ID $end
$var parameter 32 ; ST_IF $end
$var parameter 32 < ST_WB $end
$var reg 32 = REGISTER_TEST [31:0] $end
$var reg 32 > alu_out [31:0] $end
$var reg 13 ? b_imm [12:0] $end
$var reg 3 @ funct3 [2:0] $end
$var reg 7 A funct7 [6:0] $end
$var reg 12 B i_imm [11:0] $end
$var reg 21 C j_imm [20:0] $end
$var reg 7 D opcode [6:0] $end
$var reg 32 E pc [31:0] $end
$var reg 32 F pc_p4 [31:0] $end
$var reg 5 G rd [4:0] $end
$var reg 32 H reg_iaddr [31:0] $end
$var reg 32 I reg_inst [31:0] $end
$var reg 32 J reg_raddr [31:0] $end
$var reg 8 K reg_tx_data [7:0] $end
$var reg 1 L reg_tx_start $end
$var reg 32 M reg_wdata [31:0] $end
$var reg 1 N reg_wen $end
$var reg 5 O rs1 [4:0] $end
$var reg 5 P rs2 [4:0] $end
$var reg 12 Q s_imm [11:0] $end
$var reg 4 R stage [3:0] $end
$var reg 32 S u_imm [31:0] $end
$var integer 32 T i [31:0] $end
$upscope $end
$scope module mem0 $end
$var wire 1 $ clock $end
$var wire 32 U iaddr [31:0] $end
$var wire 32 V raddr [31:0] $end
$var wire 32 W wdata [31:0] $end
$var wire 1 % wen $end
$var wire 32 X rdata [31:0] $end
$var wire 32 Y inst [31:0] $end
$var reg 32 Z reg_raddr [31:0] $end
$var integer 32 [ i [31:0] $end
$upscope $end
$scope module uart0 $end
$var wire 1 " LED $end
$var wire 1 $ clock $end
$var wire 8 \ data_in [7:0] $end
$var wire 1 ' start $end
$var wire 1 ! tx $end
$var wire 1 ] tx_clock $end
$var wire 1 ) tx_busy $end
$var parameter 32 ^ FPGA_FREQ $end
$var parameter 32 _ S_END $end
$var parameter 32 ` S_IDLE $end
$var parameter 32 a S_P $end
$var parameter 32 b S_SEND $end
$var parameter 32 c S_START $end
$var parameter 65 d TX_CLOCK_COUNT_MAX $end
$var parameter 32 e UART_FREQ $end
$var reg 32 f clock_count [31:0] $end
$var reg 8 g data [7:0] $end
$var reg 1 h led_flag $end
$var reg 8 i local_in [7:0] $end
$var reg 1 j local_start $end
$var reg 4 k send_count [3:0] $end
$var reg 5 l state [4:0] $end
$var reg 1 m tx_reg $end
$upscope $end
$upscope $end
$upscope $end
$enddefinitions $end
$comment Show the parameter values. $end
$dumpall
b11100001000000000 e
b11101001 d
b1 c
b10 b
b11 a
b0 `
b100 _
b11011 ^
b100 <
b0 ;
b1 :
b10 9
b11 8
b1 #
$end
#0
$dumpvars
1m
b0 l
b0 k
xj
bx i
xh
bx g
b0 f
1]
bx \
b1000000 [
b0 Z
b1000001010001000100011 Y
b1000001010001000100011 X
b0 W
b0 V
b0 U
b100000 T
bx S
b0 R
bx Q
bx P
bx O
0N
b0 M
xL
bx K
b0 J
b0 I
b0 H
bx G
bx F
b0 E
bx D
bx C
bx B
bx A
bx @
bx ?
b0 >
bx =
b0xxxxxxxxxxxxxxxxxxxxxxxxxxxxxxx 7
b0 6
b1000001010001000100011 5
b0 4
b1000001010001000100011 3
b0xxxxxxxxxxxxxxxxxxxxxxxxxxxxxxx 2
b0 1
bx 0
bx /
bx .
b0 -
b1000001010001000100011 ,
b0 +
b1000001010001000100011 *
0)
bx (
x'
b0 &
0%
0$
x"
1!
$end
#1
0]
b1 f
b1 R
b100 F
b1000001010001000100011 I
b0 =
b0 (
b0 0
b0 \
b0 K
1'
1L
1$
#2
0$
#3
b100 2
b10 7
b10 R
b100 Q
b10 B
b1000001 /
b10 P
b0 .
b1 O
1j
b0 i
b10 f
b1010000000000010 C
b1000001010xxxxxxxxxxxx S
b100 ?
b0 A
b10 @
b100 G
b100011 D
1$
#4
0$
#5
b11 f
b11 R
b100 >
1$
#6
0$
#7
b100 R
b100 f
b1000001 &
b1000001 1
b1000001 W
b1000001 M
1%
1N
b0 *
b0 3
b0 X
b100 +
b100 4
b100 J
b100 V
1$
#8
0$
#9
b101 f
b0 R
b0 ,
b0 5
b0 Y
b100 -
b100 6
b100 H
b100 U
0%
0N
b0 >
b100 E
1$
#10
0$
#11
b1 R
b1000 F
b0 I
b110 f
1$
#12
0$
#13
b0 2
b0 7
b111 f
b10 R
b0 Q
b0 B
b0 /
b0 P
b0 O
b0 C
b0xxxxxxxxxxxx S
b0 ?
b0 @
b0 G
b0 D
1$
#14
0$
#15
b11 R
b1000 f
1$
#16
0$
#17
b1001 f
b100 R
b0 &
b0 1
b0 W
b0 M
b1000001010001000100011 *
b1000001010001000100011 3
b1000001010001000100011 X
b0 +
b0 4
b0 J
b0 V
1$
#18
0$
#19
b0 R
b1010 f
b1000 -
b1000 6
b1000 H
b1000 U
b1000 E
1$
#20
0$
#21
b1011 f
b1 R
b1100 F
1$
#22
0$
#23
b10 R
b1100 f
1$
#24
0$
#25
b1101 f
b11 R
1$
#26
0$
#27
b100 R
b1110 f
1$
#28
0$
#29
b1111 f
b0 R
b1100 -
b1100 6
b1100 H
b1100 U
b1100 E
1$
#30
0$
#31
b1 R
b10000 F
b10000 f
1$
#32
0$
#33
b10001 f
b10 R
1$
#34
0$
#35
b11 R
b10010 f
1$
#36
0$
#37
b10011 f
b100 R
1$
#38
0$
#39
b0 R
b10100 f
b10000 -
b10000 6
b10000 H
b10000 U
b10000 E
1$
#40
0$
#41
b10101 f
b1 R
b10100 F
1$
#42
0$
#43
b10 R
b10110 f
1$
#44
0$
#45
b10111 f
b11 R
1$
#46
0$
#47
b100 R
b11000 f
1$
#48
0$
#49
b11001 f
b0 R
b10100 -
b10100 6
b10100 H
b10100 U
b10100 E
1$
#50
0$
#51
b1 R
b11000 F
b11010 f
1$
#52
0$
#53
b11011 f
b10 R
1$
#54
0$
#55
b11 R
b11100 f
1$
#56
0$
#57
b11101 f
b100 R
1$
#58
0$
#59
b0 R
b11110 f
b11000 -
b11000 6
b11000 H
b11000 U
b11000 E
1$
#60
0$
#61
b11111 f
b1 R
b11100 F
1$
#62
0$
#63
b10 R
b100000 f
1$
#64
0$
#65
b100001 f
b11 R
1$
#66
0$
#67
b100 R
b100010 f
1$
#68
0$
#69
b100011 f
b0 R
b11100 -
b11100 6
b11100 H
b11100 U
b11100 E
1$
#70
0$
#71
b1 R
b100000 F
b100100 f
1$
#72
0$
#73
b100101 f
b10 R
1$
#74
0$
#75
b11 R
b100110 f
1$
#76
0$
#77
b100111 f
b100 R
1$
#78
0$
#79
b0 R
b101000 f
b0xxxxxxxxxxxxxxxxxxxxxxxx ,
b0xxxxxxxxxxxxxxxxxxxxxxxx 5
b0xxxxxxxxxxxxxxxxxxxxxxxx Y
b100000 -
b100000 6
b100000 H
b100000 U
b100000 E
1$
#80
0$
#81
b101001 f
b1 R
b100100 F
b0xxxxxxxxxxxxxxxxxxxxxxxx I
1$
#82
0$
#83
b0xxxxx 2
b0xxxx 7
b10 R
b0xxxxx Q
b0xxxx B
bx /
b0xxxx P
bx .
bx O
b101010 f
b0xxxxxxxxx0000000xxx0 C
b0xxxxxxxxxxxxxxxxxxxxxxxx S
b0xxxxx ?
bx @
bx G
bx D
1$
#84
0$
#85
b101011 f
b11 R
1$
#86
0$
#87
b100 R
b101100 f
bx &
bx 1
bx W
bx M
x%
xN
1$
#88
0$
#89
b101101 f
b0 R
bx ,
bx 5
bx Y
b100100 -
b100100 6
b100100 H
b100100 U
0%
0N
b100100 E
1$
#90
0$
#91
b1 R
b101000 F
bx I
b101110 f
1$
#92
0$
#93
b0xxxxxxxxxxxxxxxxxxxxxxxxxxxxxxx 2
b0xxxxxxxxxxxxxxxxxxxxxxxxxxxxxxx 7
b101111 f
b10 R
bx Q
bx B
bx P
bx0 C
bx S
b0xxxxxxxxxxxx ?
bx A
1$
#94
0$
#95
b11 R
b110000 f
1$
#96
0$
#97
b110001 f
b100 R
x%
xN
1$
#98
0$
#99
b0 R
b110010 f
b101000 -
b101000 6
b101000 H
b101000 U
0%
0N
b101000 E
1$
#100
0$
#101
b110011 f
b1 R
b101100 F
1$
#102
0$
#103
b10 R
b110100 f
1$
#104
0$
#105
b110101 f
b11 R
1$
#106
0$
#107
b100 R
b110110 f
x%
xN
1$
#108
0$
#109
b110111 f
b0 R
b101100 -
b101100 6
b101100 H
b101100 U
0%
0N
b101100 E
1$
#110
0$
#111
b1 R
b110000 F
b111000 f
1$
#112
0$
#113
b111001 f
b10 R
1$
#114
0$
#115
b11 R
b111010 f
1$
#116
0$
#117
b111011 f
b100 R
x%
xN
1$
#118
0$
#119
b0 R
b111100 f
b110000 -
b110000 6
b110000 H
b110000 U
0%
0N
b110000 E
1$
#120
0$
#121
b111101 f
b1 R
b110100 F
1$
#122
0$
#123
b10 R
b111110 f
1$
#124
0$
#125
b111111 f
b11 R
1$
#126
0$
#127
b100 R
b1000000 f
x%
xN
1$
#128
0$
#129
b1000001 f
b0 R
b110100 -
b110100 6
b110100 H
b110100 U
0%
0N
b110100 E
1$
#130
0$
#131
b1 R
b111000 F
b1000010 f
1$
#132
0$
#133
b1000011 f
b10 R
1$
#134
0$
#135
b11 R
b1000100 f
1$
#136
0$
#137
b1000101 f
b100 R
x%
xN
1$
#138
0$
#139
b0 R
b1000110 f
b111000 -
b111000 6
b111000 H
b111000 U
0%
0N
b111000 E
1$
#140
0$
#141
b1000111 f
b1 R
b111100 F
1$
#142
0$
#143
b10 R
b1001000 f
1$
#144
0$
#145
b1001001 f
b11 R
1$
#146
0$
#147
b100 R
b1001010 f
x%
xN
1$
#148
0$
#149
b1001011 f
b0 R
b111100 -
b111100 6
b111100 H
b111100 U
0%
0N
b111100 E
1$
#150
0$
#151
b1 R
b1000000 F
b1001100 f
1$
#152
0$
#153
b1001101 f
b10 R
1$
#154
0$
#155
b11 R
b1001110 f
1$
#156
0$
#157
b1001111 f
b100 R
x%
xN
1$
#158
0$
#159
b0 R
b1010000 f
b1000000 -
b1000000 6
b1000000 H
b1000000 U
0%
0N
b1000000 E
1$
#160
0$
#161
b1010001 f
b1 R
b1000100 F
1$
#162
0$
#163
b10 R
b1010010 f
1$
#164
0$
#165
b1010011 f
b11 R
1$
#166
0$
#167
b100 R
b1010100 f
x%
xN
1$
#168
0$
#169
b1010101 f
b0 R
b1000100 -
b1000100 6
b1000100 H
b1000100 U
0%
0N
b1000100 E
1$
#170
0$
#171
b1 R
b1001000 F
b1010110 f
1$
#172
0$
#173
b1010111 f
b10 R
1$
#174
0$
#175
b11 R
b1011000 f
1$
#176
0$
#177
b1011001 f
b100 R
x%
xN
1$
#178
0$
#179
b0 R
b1011010 f
b1001000 -
b1001000 6
b1001000 H
b1001000 U
0%
0N
b1001000 E
1$
#180
0$
#181
b1011011 f
b1 R
b1001100 F
1$
#182
0$
#183
b10 R
b1011100 f
1$
#184
0$
#185
b1011101 f
b11 R
1$
#186
0$
#187
b100 R
b1011110 f
x%
xN
1$
#188
0$
#189
b1011111 f
b0 R
b1001100 -
b1001100 6
b1001100 H
b1001100 U
0%
0N
b1001100 E
1$
#190
0$
#191
b1 R
b1010000 F
b1100000 f
1$
#192
0$
#193
b1100001 f
b10 R
1$
#194
0$
#195
b11 R
b1100010 f
1$
#196
0$
#197
b1100011 f
b100 R
x%
xN
1$
#198
0$
#199
b0 R
b1100100 f
b1010000 -
b1010000 6
b1010000 H
b1010000 U
0%
0N
b1010000 E
1$
#200
0$
#201
b1100101 f
b1 R
b1010100 F
1$
#202
0$
#203
b10 R
b1100110 f
1$
#204
0$
#205
b1100111 f
b11 R
1$
#206
0$
#207
b100 R
b1101000 f
x%
xN
1$
#208
0$
#209
b1101001 f
b0 R
b1010100 -
b1010100 6
b1010100 H
b1010100 U
0%
0N
b1010100 E
1$
#210
0$
#211
b1 R
b1011000 F
b1101010 f
1$
#212
0$
#213
b1101011 f
b10 R
1$
#214
0$
#215
b11 R
b1101100 f
1$
#216
0$
#217
b1101101 f
b100 R
x%
xN
1$
#218
0$
#219
b0 R
b1101110 f
b1011000 -
b1011000 6
b1011000 H
b1011000 U
0%
0N
b1011000 E
1$
#220
0$
#221
b1101111 f
b1 R
b1011100 F
1$
#222
0$
#223
b10 R
b1110000 f
1$
#224
0$
#225
b1110001 f
b11 R
1$
#226
0$
#227
b100 R
b1110010 f
x%
xN
1$
#228
0$
#229
b1110011 f
b0 R
b1011100 -
b1011100 6
b1011100 H
b1011100 U
0%
0N
b1011100 E
1$
#230
0$
#231
b1 R
b1100000 F
b1110100 f
1$
#232
0$
#233
b1110101 f
b10 R
1$
#234
0$
#235
b11 R
b1110110 f
1$
#236
0$
#237
b1110111 f
b100 R
x%
xN
1$
#238
0$
#239
b0 R
b1111000 f
b1100000 -
b1100000 6
b1100000 H
b1100000 U
0%
0N
b1100000 E
1$
#240
0$
#241
b1111001 f
b1 R
b1100100 F
1$
#242
0$
#243
b10 R
b1111010 f
1$
#244
0$
#245
b1111011 f
b11 R
1$
#246
0$
#247
b100 R
b1111100 f
x%
xN
1$
#248
0$
#249
b1111101 f
b0 R
b1100100 -
b1100100 6
b1100100 H
b1100100 U
0%
0N
b1100100 E
1$
#250
0$
#251
b1 R
b1101000 F
b1111110 f
1$
#252
0$
#253
b1111111 f
b10 R
1$
#254
0$
#255
b11 R
b10000000 f
1$
#256
0$
#257
b10000001 f
b100 R
x%
xN
1$
#258
0$
#259
b0 R
b10000010 f
b1101000 -
b1101000 6
b1101000 H
b1101000 U
0%
0N
b1101000 E
1$
#260
0$
#261
b10000011 f
b1 R
b1101100 F
1$
#262
0$
#263
b10 R
b10000100 f
1$
#264
0$
#265
b10000101 f
b11 R
1$
#266
0$
#267
b100 R
b10000110 f
x%
xN
1$
#268
0$
#269
b10000111 f
b0 R
b1101100 -
b1101100 6
b1101100 H
b1101100 U
0%
0N
b1101100 E
1$
#270
0$
#271
b1 R
b1110000 F
b10001000 f
1$
#272
0$
#273
b10001001 f
b10 R
1$
#274
0$
#275
b11 R
b10001010 f
1$
#276
0$
#277
b10001011 f
b100 R
x%
xN
1$
#278
0$
#279
b0 R
b10001100 f
b1110000 -
b1110000 6
b1110000 H
b1110000 U
0%
0N
b1110000 E
1$
#280
0$
#281
b10001101 f
b1 R
b1110100 F
1$
#282
0$
#283
b10 R
b10001110 f
1$
#284
0$
#285
b10001111 f
b11 R
1$
#286
0$
#287
b100 R
b10010000 f
x%
xN
1$
#288
0$
#289
b10010001 f
b0 R
b1110100 -
b1110100 6
b1110100 H
b1110100 U
0%
0N
b1110100 E
1$
#290
0$
#291
b1 R
b1111000 F
b10010010 f
1$
#292
0$
#293
b10010011 f
b10 R
1$
#294
0$
#295
b11 R
b10010100 f
1$
#296
0$
#297
b10010101 f
b100 R
x%
xN
1$
#298
0$
#299
b0 R
b10010110 f
b1111000 -
b1111000 6
b1111000 H
b1111000 U
0%
0N
b1111000 E
1$
#300
0$
#301
b10010111 f
b1 R
b1111100 F
1$
#302
0$
#303
b10 R
b10011000 f
1$
#304
0$
#305
b10011001 f
b11 R
1$
#306
0$
#307
b100 R
b10011010 f
x%
xN
1$
#308
0$
#309
b10011011 f
b0 R
b1111100 -
b1111100 6
b1111100 H
b1111100 U
0%
0N
b1111100 E
1$
#310
0$
#311
b1 R
b10000000 F
b10011100 f
1$
#312
0$
#313
b10011101 f
b10 R
1$
#314
0$
#315
b11 R
b10011110 f
1$
#316
0$
#317
b10011111 f
b100 R
x%
xN
1$
#318
0$
#319
b0 R
b10100000 f
b10000000 -
b10000000 6
b10000000 H
b10000000 U
0%
0N
b10000000 E
1$
#320
0$
#321
b10100001 f
b1 R
b10000100 F
1$
#322
0$
#323
b10 R
b10100010 f
1$
#324
0$
#325
b10100011 f
b11 R
1$
#326
0$
#327
b100 R
b10100100 f
x%
xN
1$
#328
0$
#329
b10100101 f
b0 R
b10000100 -
b10000100 6
b10000100 H
b10000100 U
0%
0N
b10000100 E
1$
#330
0$
#331
b1 R
b10001000 F
b10100110 f
1$
#332
0$
#333
b10100111 f
b10 R
1$
#334
0$
#335
b11 R
b10101000 f
1$
#336
0$
#337
b10101001 f
b100 R
x%
xN
1$
#338
0$
#339
b0 R
b10101010 f
b10001000 -
b10001000 6
b10001000 H
b10001000 U
0%
0N
b10001000 E
1$
#340
0$
#341
b10101011 f
b1 R
b10001100 F
1$
#342
0$
#343
b10 R
b10101100 f
1$
#344
0$
#345
b10101101 f
b11 R
1$
#346
0$
#347
b100 R
b10101110 f
x%
xN
1$
#348
0$
#349
b10101111 f
b0 R
b10001100 -
b10001100 6
b10001100 H
b10001100 U
0%
0N
b10001100 E
1$
#350
0$
#351
b1 R
b10010000 F
b10110000 f
1$
#352
0$
#353
b10110001 f
b10 R
1$
#354
0$
#355
b11 R
b10110010 f
1$
#356
0$
#357
b10110011 f
b100 R
x%
xN
1$
#358
0$
#359
b0 R
b10110100 f
b10010000 -
b10010000 6
b10010000 H
b10010000 U
0%
0N
b10010000 E
1$
#360
0$
#361
b10110101 f
b1 R
b10010100 F
1$
#362
0$
#363
b10 R
b10110110 f
1$
#364
0$
#365
b10110111 f
b11 R
1$
#366
0$
#367
b100 R
b10111000 f
x%
xN
1$
#368
0$
#369
b10111001 f
b0 R
b10010100 -
b10010100 6
b10010100 H
b10010100 U
0%
0N
b10010100 E
1$
#370
0$
#371
b1 R
b10011000 F
b10111010 f
1$
#372
0$
#373
b10111011 f
b10 R
1$
#374
0$
#375
b11 R
b10111100 f
1$
#376
0$
#377
b10111101 f
b100 R
x%
xN
1$
#378
0$
#379
b0 R
b10111110 f
b10011000 -
b10011000 6
b10011000 H
b10011000 U
0%
0N
b10011000 E
1$
#380
0$
#381
b10111111 f
b1 R
b10011100 F
1$
#382
0$
#383
b10 R
b11000000 f
1$
#384
0$
#385
b11000001 f
b11 R
1$
#386
0$
#387
b100 R
b11000010 f
x%
xN
1$
#388
0$
#389
b11000011 f
b0 R
b10011100 -
b10011100 6
b10011100 H
b10011100 U
0%
0N
b10011100 E
1$
#390
0$
#391
b1 R
b10100000 F
b11000100 f
1$
#392
0$
#393
b11000101 f
b10 R
1$
#394
0$
#395
b11 R
b11000110 f
1$
#396
0$
#397
b11000111 f
b100 R
x%
xN
1$
#398
0$
#399
b0 R
b11001000 f
b10100000 -
b10100000 6
b10100000 H
b10100000 U
0%
0N
b10100000 E
1$
#400
0$
#401
b11001001 f
b1 R
b10100100 F
1$
#402
0$
#403
b10 R
b11001010 f
1$
#404
0$
#405
b11001011 f
b11 R
1$
#406
0$
#407
b100 R
b11001100 f
x%
xN
1$
#408
0$
#409
b11001101 f
b0 R
b10100100 -
b10100100 6
b10100100 H
b10100100 U
0%
0N
b10100100 E
1$
#410
0$
#411
b1 R
b10101000 F
b11001110 f
1$
#412
0$
#413
b11001111 f
b10 R
1$
#414
0$
#415
b11 R
b11010000 f
1$
#416
0$
#417
b11010001 f
b100 R
x%
xN
1$
#418
0$
#419
b0 R
b11010010 f
b10101000 -
b10101000 6
b10101000 H
b10101000 U
0%
0N
b10101000 E
1$
#420
0$
#421
b11010011 f
b1 R
b10101100 F
1$
#422
0$
#423
b10 R
b11010100 f
1$
#424
0$
#425
b11010101 f
b11 R
1$
#426
0$
#427
b100 R
b11010110 f
x%
xN
1$
#428
0$
#429
b11010111 f
b0 R
b10101100 -
b10101100 6
b10101100 H
b10101100 U
0%
0N
b10101100 E
1$
#430
0$
#431
b1 R
b10110000 F
b11011000 f
1$
#432
0$
#433
b11011001 f
b10 R
1$
#434
0$
#435
b11 R
b11011010 f
1$
#436
0$
#437
b11011011 f
b100 R
x%
xN
1$
#438
0$
