src/core.v
module CORE(
    input clock,

// UART
    output tx_start,
    output [7:0] tx_data,

// Memory
    output [31:0] raddr,
    output [31:0] iaddr,
    output wen,
    output [31:0] wdata,
    input [31:0] inst,
    input [31:0] rdata
);

    reg [31:0] register [31:0];
    reg [31:0] REGISTER_TEST;

    reg [7:0] reg_tx_data;
    reg reg_tx_start;

    reg [31:0] pc;
    reg [31:0] pc_p4;
    reg [31:0] reg_inst;
    reg [31:0] reg_iaddr;
    reg [31:0] reg_raddr;
    reg [31:0] reg_wdata;
    reg reg_wen;

    reg [6:0] opcode;
    reg [4:0] rd;
    reg [2:0] funct3;
    reg [4:0] rs1;
    reg [4:0] rs2;
    reg [6:0] funct7;

    wire [31:0] rs1_data;
    wire [31:0] rs2_data;

    reg [11:0] i_imm;
    reg [31:0] i_imm_sext;
    reg [11:0] s_imm;
    reg [31:0] s_imm_sext;
    reg [12:0] b_imm;
    reg [31:0] u_imm;
    reg [20:0] j_imm;

    reg [31:0] alu_out;

    localparam ST_IF = 0;
    localparam ST_ID = 1;
    localparam ST_EX = 2;
    localparam ST_ACCESS = 3;
    localparam ST_WB = 4;
    reg [3:0] stage;

    integer i;
    initial begin
        for (i=0;i<32;i=i+1) register[i] <= 31'b0;
        register[0] <= 32'b00000000000000000000000000000000;
        register[1] <= 32'b00000000000000000000000000000000;
        register[2] <= 32'b00000000000000000000000001000001;

        pc = 0;
        reg_inst = 0;
        reg_iaddr = 0;
        reg_raddr = 0;
        reg_wdata = 0;
        reg_wen = 0;
        alu_out = 0;
        stage = ST_IF;
    end

    always @(posedge clock) begin
        case (stage)
            ST_IF: begin
                reg_tx_start <= 1;
                reg_tx_data <= rdata[31:24];
                REGISTER_TEST <= register[1][31:0];
                reg_iaddr <= pc;
                reg_inst <= inst;
                pc_p4 <= pc + 4;

                stage <= ST_ID;
            end

            ST_ID: begin
                opcode = reg_inst[0+:7];
                rd = reg_inst[7+:5];
                funct3 = reg_inst[12+:3];
                rs1 <= reg_inst[19:15];
                rs2 <= reg_inst[24:20];
                funct7 = reg_inst[25+:7];

                i_imm <= reg_inst[20+:12];
                i_imm_sext <= { {20{i_imm[11]}}, i_imm[10:0] };
                s_imm <= { reg_inst[31:25], reg_inst[11:7] };
                s_imm_sext <= { {20{s_imm[11]}}, s_imm[10:0] };
                b_imm = { reg_inst[25+:7], reg_inst[7+:5] };
                u_imm[31:12] = reg_inst[31:12];
                j_imm = {{12{reg_inst[31]}}, reg_inst[19:12], reg_inst[20], reg_inst[30:25], reg_inst[24:21], 1'b0};

                stage <= ST_EX;
            end

            ST_EX: begin

                alu_out = rs1_data + s_imm;

                stage <= ST_ACCESS;
            end

            ST_ACCESS: begin
                reg_raddr = alu_out;
                reg_wen = opcode == 7'b0100011;
                reg_wdata = rs2_data;

                stage <= ST_WB;
            end

            ST_WB: begin
                pc <= pc_p4;
                reg_wen <= 0;
                reg_raddr = 4;

                stage <= ST_IF;
            end
        endcase
    end

    assign rs1_data = register[rs1];
    assign rs2_data = register[rs2];

    assign tx_start = reg_tx_start;
    assign tx_data = reg_tx_data;

    assign iaddr = reg_iaddr;
    assign raddr = reg_raddr;
    assign wdata = reg_wdata;
    assign wen = reg_wen;

endmodule

src/memory.v
module MEMORY(
    input clock,

    input [31:0] raddr,
    input [31:0] iaddr,
    input wen,
    input [31:0] wdata,
    
    output [31:0] inst,
    output [31:0] rdata
);

    reg [7:0] mem [512:0];
    
    reg [31:0] reg_raddr;
    
    integer i;
    initial begin
        for (i=0;i<64;i=i+1) mem[i] <= 0;
        mem[0] <= 8'b00000000;
        mem[1] <= 8'b00100000;
        mem[2] <= 8'b10100010;
        mem[3] <= 8'b00100011;

        mem[0] <= 8'b00000000;
        mem[1] <= 8'b00100000;
        mem[2] <= 8'b10100010;
        mem[3] <= 8'b00100011;
        reg_raddr <= 32'b0;
    end

    always @(posedge clock) begin
        if (wen == 1'b1) begin
            mem[raddr] = wdata[0 +:8];
            mem[raddr+1] = wdata[8 +:8];
            mem[raddr+2] = wdata[16 +:8];
            mem[raddr+3] = wdata[24 +:8];
        end
    end

    assign inst = {
        mem[iaddr+0],
        mem[iaddr+1],
        mem[iaddr+2],
        mem[iaddr+3]
    };

    assign rdata = {
        mem[raddr+0],
        mem[raddr+1],
        mem[raddr+2],
        mem[raddr+3]
    };

endmodule

src/uart.v
module UART(
    input clock,

    input [7:0] data_in,
    input start,

    output tx_busy,
    output tx,
    output LED
);

    // UART Clock
    localparam FPGA_FREQ = 27; // MHz
    localparam UART_FREQ = 115200;
    localparam TX_CLOCK_COUNT_MAX = FPGA_FREQ * 1000000 / UART_FREQ - 1;

    reg [31:0] clock_count;

    reg led_flag;
    assign LED = led_flag;

    wire tx_clock = (clock_count == 0);

    initial begin
        clock_count = 0;
    end

    always @(posedge clock) begin
        if (clock_count == TX_CLOCK_COUNT_MAX) begin
            clock_count <= 0;
            led_flag <= ~led_flag;
        end else begin
            clock_count <= clock_count + 1;
        end
    end


    // State Machine
    localparam S_IDLE = 0;
    localparam S_START = 1;
    localparam S_SEND = 2;
    localparam S_P = 3;
    localparam S_END = 4;

    reg [4:0] state;
    reg [3:0] send_count;

    reg tx_reg;
    reg [7:0] data;
    reg [7:0] local_in;
    reg local_start;

    assign tx = tx_reg;

    always @(posedge clock) begin
        local_in <= data_in;
        local_start <= start;
    end

    assign tx_busy = (state != S_IDLE);

    initial begin
        state = S_IDLE;
        send_count = 0;
        tx_reg = 1'b1;
    end

    always @(posedge clock) begin
        case (state)
            S_IDLE:
                if (tx_clock) begin
                    if (local_start) begin
                        tx_reg <= 1'b1;
                        state <= S_START;
                    end else begin
                        tx_reg <= 1'b1;
                        state <= S_IDLE;
                    end
                end

            S_START: 
                if (tx_clock) begin
                    tx_reg <= 1'b0;
                    data <= local_in;
                    send_count <= 0;
                    state <= S_SEND;
                end else begin
                    tx_reg <= 1'b0;
                    state <= S_START;
                end

            S_SEND:
                if (tx_clock) begin
                    tx_reg <= data[send_count];
                    if (send_count == 3'd7) begin
                        state <= S_P;
                    end else begin
                        send_count <= send_count + 1;
                        state <= S_SEND;
                    end
                end else begin
                    tx_reg <= data[send_count];
                    state <= S_SEND;
                end

            S_P:
                if (tx_clock) begin
                    tx_reg <= 1'b1;
                    state <= S_END;
                end else begin
                    tx_reg <= 1'b1;
                    state <= S_P;
                end

            S_END:
                if (tx_clock) begin
                    tx_reg <= 1'b1;
                    state <= S_IDLE;
                end else begin
                    tx_reg <= 1'b1;
                    state <= S_END;
                end
        endcase
    end

endmodule

src/top.v
module TOP(
    input clock,
    output LED,
    output tx
);

    wire tx_busy;
    wire tx_start;
    wire [7:0] tx_data;

    UART uart0(
        .clock(clock),
        .tx(tx),
        .tx_busy(tx_busy),
        .start(tx_start),
        .data_in(tx_data),
        .LED(LED)
    );

    wire [31:0] inst;
    wire [31:0] rdata;
    wire [31:0] raddr;
    wire [31:0] iaddr;
    wire [31:0] wdata;
    wire wen;
    MEMORY mem0(
        .clock(clock),
        .raddr(raddr),
        .iaddr(iaddr),
        .wen(wen),
        .wdata(wdata),
        .inst(inst),
        .rdata(rdata)
    );

    CORE core0(
        .clock(clock),
        .tx_start(tx_start),
        .tx_data(tx_data),
        .raddr(raddr),
        .iaddr(iaddr),
        .wen(wen),
        .wdata(wdata),
        .inst(inst),
        .rdata(rdata)
    );
/*
    localparam MEM_WRITE = 0;
    localparam MEM_READ = 1;
    localparam MEM_IDLE = 2;

    localparam WAIT_TIME = 200000;
    reg [31:0] clock_count;
    reg [7:0] send_count;
    reg [3:0] state;
    wire [4 * 8:0] str = "test";
    initial begin
        clock_count = WAIT_TIME;
        send_count = 0;
        state = MEM_WRITE;
        tx_start = 1'b0;
        tx_data = 8'b0;
    end

    always @(posedge clock) begin
        if (clock_count == WAIT_TIME) begin

            case (state)
                MEM_WRITE: begin
                    raddr <= 32'b0;
                    wdata <= "C";
                    wen <= 1'b1;
                    state <= MEM_READ;
                end

                MEM_READ: begin
                    wen <= 1'b0;
                    raddr <= 32'b0;
                    if (tx_busy == 1'b0) begin
                        tx_data <= rdata[0 +:8];
                        tx_start <= 1'b1;
                    end
                    state <= MEM_IDLE;
                end

                MEM_IDLE:
                    state <= MEM_WRITE;
            endcase

            clock_count <= 0;
        end else begin
            clock_count <= clock_count + 1;
            tx_start <= 1'b1;
        end
    end*/

endmodule

src/uart_tb.v
module memory_tb;

    parameter RATE = 1;

    initial begin
        $dumpfile("tb_memory.vcd");
        $dumpvars(3, memory_tb);

        # (10000) $finish;
    end

    reg clk = 0;
    always #(RATE) clk = !clk;
    wire LED;
    wire TX;

    TOP top(
        .clock(clk),
        .LED(LED),
        .tx(TX)
    );

endmodule

src/tb_memory.vcd
$date
	Thu May 18 09:13:37 2023
$end
$version
	Icarus Verilog
$end
$timescale
	1s
$end
$scope module memory_tb $end
$var wire 1 ! TX $end
$var wire 1 " LED $end
$var parameter 32 # RATE $end
$var reg 1 $ clk $end
$scope module top $end
$var wire 1 $ clock $end
$var wire 1 % wen $end
$var wire 32 & wdata [31:0] $end
$var wire 1 ' tx_start $end
$var wire 8 ( tx_data [7:0] $end
$var wire 1 ) tx_busy $end
$var wire 1 ! tx $end
$var wire 32 * rdata [31:0] $end
$var wire 32 + raddr [31:0] $end
$var wire 32 , inst [31:0] $end
$var wire 32 - iaddr [31:0] $end
$var wire 1 " LED $end
$scope module core0 $end
$var wire 1 $ clock $end
$var wire 32 . rs1_data [31:0] $end
$var wire 32 / rs2_data [31:0] $end
$var wire 8 0 tx_data [7:0] $end
$var wire 1 ' tx_start $end
$var wire 32 1 wdata [31:0] $end
$var wire 1 % wen $end
$var wire 32 2 rdata [31:0] $end
$var wire 32 3 raddr [31:0] $end
$var wire 32 4 inst [31:0] $end
$var wire 32 5 iaddr [31:0] $end
$var parameter 32 6 ST_ACCESS $end
$var parameter 32 7 ST_EX $end
$var parameter 32 8 ST_ID $end
$var parameter 32 9 ST_IF $end
$var parameter 32 : ST_WB $end
$var reg 32 ; REGISTER_TEST [31:0] $end
$var reg 32 < alu_out [31:0] $end
$var reg 13 = b_imm [12:0] $end
$var reg 3 > funct3 [2:0] $end
$var reg 7 ? funct7 [6:0] $end
$var reg 12 @ i_imm [11:0] $end
$var reg 32 A i_imm_sext [31:0] $end
$var reg 21 B j_imm [20:0] $end
$var reg 7 C opcode [6:0] $end
$var reg 32 D pc [31:0] $end
$var reg 32 E pc_p4 [31:0] $end
$var reg 5 F rd [4:0] $end
$var reg 32 G reg_iaddr [31:0] $end
$var reg 32 H reg_inst [31:0] $end
$var reg 32 I reg_raddr [31:0] $end
$var reg 8 J reg_tx_data [7:0] $end
$var reg 1 K reg_tx_start $end
$var reg 32 L reg_wdata [31:0] $end
$var reg 1 M reg_wen $end
$var reg 5 N rs1 [4:0] $end
$var reg 5 O rs2 [4:0] $end
$var reg 12 P s_imm [11:0] $end
$var reg 32 Q s_imm_sext [31:0] $end
$var reg 4 R stage [3:0] $end
$var reg 32 S u_imm [31:0] $end
$var integer 32 T i [31:0] $end
$upscope $end
$scope module mem0 $end
$var wire 1 $ clock $end
$var wire 32 U iaddr [31:0] $end
$var wire 32 V raddr [31:0] $end
$var wire 32 W wdata [31:0] $end
$var wire 1 % wen $end
$var wire 32 X rdata [31:0] $end
$var wire 32 Y inst [31:0] $end
$var reg 32 Z reg_raddr [31:0] $end
$var integer 32 [ i [31:0] $end
$upscope $end
$scope module uart0 $end
$var wire 1 " LED $end
$var wire 1 $ clock $end
$var wire 8 \ data_in [7:0] $end
$var wire 1 ' start $end
$var wire 1 ! tx $end
$var wire 1 ] tx_clock $end
$var wire 1 ) tx_busy $end
$var parameter 32 ^ FPGA_FREQ $end
$var parameter 32 _ S_END $end
$var parameter 32 ` S_IDLE $end
$var parameter 32 a S_P $end
$var parameter 32 b S_SEND $end
$var parameter 32 c S_START $end
$var parameter 65 d TX_CLOCK_COUNT_MAX $end
$var parameter 32 e UART_FREQ $end
$var reg 32 f clock_count [31:0] $end
$var reg 8 g data [7:0] $end
$var reg 1 h led_flag $end
$var reg 8 i local_in [7:0] $end
$var reg 1 j local_start $end
$var reg 4 k send_count [3:0] $end
$var reg 5 l state [4:0] $end
$var reg 1 m tx_reg $end
$upscope $end
$upscope $end
$upscope $end
$enddefinitions $end
$comment Show the parameter values. $end
$dumpall
b11100001000000000 e
b11101001 d
b1 c
b10 b
b11 a
b0 `
b100 _
b11011 ^
b100 :
b0 9
b1 8
b10 7
b11 6
b1 #
$end
#0
$dumpvars
1m
b0 l
b0 k
xj
bx i
xh
bx g
b0 f
1]
bx \
b1000000 [
b0 Z
b1000001010001000100011 Y
b1000001010001000100011 X
b0 W
b0 V
b0 U
b100000 T
bx S
b0 R
bx Q
bx P
bx O
bx N
0M
b0 L
xK
bx J
b0 I
b0 H
b0 G
bx F
bx E
b0 D
bx C
bx B
bx A
bx @
bx ?
bx >
bx =
b0 <
bx ;
b0 5
b1000001010001000100011 4
b0 3
b1000001010001000100011 2
b0 1
bx 0
bx /
bx .
b0 -
b1000001010001000100011 ,
b0 +
b1000001010001000100011 *
0)
bx (
x'
b0 &
0%
0$
x"
1!
$end
#1
0]
b1 f
b1 R
b100 E
b1000001010001000100011 H
b0 ;
b0 (
b0 0
b0 \
b0 J
1'
1K
1$
#2
0$
#3
b10 R
b0xxxxxxxxxxxxxxxxxxxxxxxxxxxxxxx Q
b100 P
b0xxxxxxxxxxxxxxxxxxxxxxxxxxxxxxx A
b10 @
b1000001 /
b10 O
b0 .
b1 N
1j
b0 i
b10 f
b1010000000000010 B
b1000001010xxxxxxxxxxxx S
b100 =
b0 ?
b10 >
b100 F
b100011 C
1$
#4
0$
#5
b11 f
b11 R
b100 <
1$
#6
0$
#7
b100 R
b100 f
b1000001 &
b1000001 1
b1000001 W
b1000001 L
1%
1M
b0 *
b0 2
b0 X
b100 +
b100 3
b100 I
b100 V
1$
#8
0$
#9
b101 f
b0 R
0%
0M
b100 D
b1000001000000000000000000000000 *
b1000001000000000000000000000000 2
b1000001000000000000000000000000 X
1$
#10
0$
#11
b1 R
b1000 E
b1000001000000000000000000000000 ,
b1000001000000000000000000000000 4
b1000001000000000000000000000000 Y
b100 -
b100 5
b100 G
b100 U
b1000001 (
b1000001 0
b1000001 \
b1000001 J
b110 f
1$
#12
0$
#13
b111 f
b1000001 i
b10 R
b100 Q
b10 A
1$
#14
0$
#15
b11 R
b1000 f
1$
#16
0$
#17
b1001 f
b100 R
1%
1M
1$
#18
0$
#19
b0 R
0%
0M
b1000 D
b1010 f
1$
#20
0$
#21
b1011 f
b1 R
b1100 E
b1000001000000000000000000000000 H
b0 ,
b0 4
b0 Y
b1000 -
b1000 5
b1000 G
b1000 U
1$
#22
0$
#23
b10 R
b10000000000 P
b10000010000 @
b0 /
b10000 O
b0 N
b1100 f
b10000010000 B
b1000001000000000000xxxxxxxxxxxx S
b10000000000 =
b100000 ?
b0 >
b0 F
b0 C
1$
#24
0$
#25
b1101 f
b11 R
b10000000000 <
1$
#26
0$
#27
b100 R
b1110 f
b0 &
b0 1
b0 W
b0 L
bx *
bx 2
bx X
b10000000000 +
b10000000000 3
b10000000000 I
b10000000000 V
1$
#28
0$
#29
b1111 f
b0 R
b1100 D
b1000001000000000000000000000000 *
b1000001000000000000000000000000 2
b1000001000000000000000000000000 X
b100 +
b100 3
b100 I
b100 V
1$
#30
0$
#31
b1 R
b10000 E
b0 H
b1100 -
b1100 5
b1100 G
b1100 U
b10000 f
1$
#32
0$
#33
b10001 f
b10 R
b10000000000 Q
b0 P
b10000010000 A
b0 @
b0 O
b0 B
b0xxxxxxxxxxxx S
b0 =
b0 ?
1$
#34
0$
#35
b11 R
b10010 f
b0 <
1$
#36
0$
#37
b10011 f
b100 R
b1000001010001000100011 *
b1000001010001000100011 2
b1000001010001000100011 X
b0 +
b0 3
b0 I
b0 V
1$
#38
0$
#39
b0 R
b10000 D
b10100 f
b1000001000000000000000000000000 *
b1000001000000000000000000000000 2
b1000001000000000000000000000000 X
b100 +
b100 3
b100 I
b100 V
1$
#40
0$
#41
b10101 f
b1 R
b10100 E
b10000 -
b10000 5
b10000 G
b10000 U
1$
#42
0$
#43
b10 R
b0 Q
b0 A
b10110 f
1$
#44
0$
#45
b10111 f
b11 R
1$
#46
0$
#47
b100 R
b11000 f
b1000001010001000100011 *
b1000001010001000100011 2
b1000001010001000100011 X
b0 +
b0 3
b0 I
b0 V
1$
#48
0$
#49
b11001 f
b0 R
b10100 D
b1000001000000000000000000000000 *
b1000001000000000000000000000000 2
b1000001000000000000000000000000 X
b100 +
b100 3
b100 I
b100 V
1$
#50
0$
#51
b1 R
b11000 E
b10100 -
b10100 5
b10100 G
b10100 U
b11010 f
1$
#52
0$
#53
b11011 f
b10 R
1$
#54
0$
#55
b11 R
b11100 f
1$
#56
0$
#57
b11101 f
b100 R
b1000001010001000100011 *
b1000001010001000100011 2
b1000001010001000100011 X
b0 +
b0 3
b0 I
b0 V
1$
#58
0$
#59
b0 R
b11000 D
b11110 f
b1000001000000000000000000000000 *
b1000001000000000000000000000000 2
b1000001000000000000000000000000 X
b100 +
b100 3
b100 I
b100 V
1$
#60
0$
#61
b11111 f
b1 R
b11100 E
b11000 -
b11000 5
b11000 G
b11000 U
1$
#62
0$
#63
b10 R
b100000 f
1$
#64
0$
#65
b100001 f
b11 R
1$
#66
0$
#67
b100 R
b100010 f
b1000001010001000100011 *
b1000001010001000100011 2
b1000001010001000100011 X
b0 +
b0 3
b0 I
b0 V
1$
#68
0$
#69
b100011 f
b0 R
b11100 D
b1000001000000000000000000000000 *
b1000001000000000000000000000000 2
b1000001000000000000000000000000 X
b100 +
b100 3
b100 I
b100 V
1$
#70
0$
#71
b1 R
b100000 E
b11100 -
b11100 5
b11100 G
b11100 U
b100100 f
1$
#72
0$
#73
b100101 f
b10 R
1$
#74
0$
#75
b11 R
b100110 f
1$
#76
0$
#77
b100111 f
b100 R
b1000001010001000100011 *
b1000001010001000100011 2
b1000001010001000100011 X
b0 +
b0 3
b0 I
b0 V
1$
#78
0$
#79
b0 R
b100000 D
b101000 f
b1000001000000000000000000000000 *
b1000001000000000000000000000000 2
b1000001000000000000000000000000 X
b100 +
b100 3
b100 I
b100 V
1$
#80
0$
#81
b101001 f
b1 R
b100100 E
b100000 -
b100000 5
b100000 G
b100000 U
1$
#82
0$
#83
b10 R
b101010 f
1$
#84
0$
#85
b101011 f
b11 R
1$
#86
0$
#87
b100 R
b101100 f
b1000001010001000100011 *
b1000001010001000100011 2
b1000001010001000100011 X
b0 +
b0 3
b0 I
b0 V
1$
#88
0$
#89
b101101 f
b0 R
b100100 D
b1000001000000000000000000000000 *
b1000001000000000000000000000000 2
b1000001000000000000000000000000 X
b100 +
b100 3
b100 I
b100 V
1$
#90
0$
#91
b1 R
b101000 E
b100100 -
b100100 5
b100100 G
b100100 U
b101110 f
1$
#92
0$
#93
b101111 f
b10 R
1$
#94
0$
#95
b11 R
b110000 f
1$
#96
0$
#97
b110001 f
b100 R
b1000001010001000100011 *
b1000001010001000100011 2
b1000001010001000100011 X
b0 +
b0 3
b0 I
b0 V
1$
#98
0$
#99
b0 R
b101000 D
b110010 f
b1000001000000000000000000000000 *
b1000001000000000000000000000000 2
b1000001000000000000000000000000 X
b100 +
b100 3
b100 I
b100 V
1$
#100
0$
#101
b110011 f
b1 R
b101100 E
b101000 -
b101000 5
b101000 G
b101000 U
1$
#102
0$
#103
b10 R
b110100 f
1$
#104
0$
#105
b110101 f
b11 R
1$
#106
0$
#107
b100 R
b110110 f
b1000001010001000100011 *
b1000001010001000100011 2
b1000001010001000100011 X
b0 +
b0 3
b0 I
b0 V
1$
#108
0$
#109
b110111 f
b0 R
b101100 D
b1000001000000000000000000000000 *
b1000001000000000000000000000000 2
b1000001000000000000000000000000 X
b100 +
b100 3
b100 I
b100 V
1$
#110
0$
#111
b1 R
b110000 E
b101100 -
b101100 5
b101100 G
b101100 U
b111000 f
1$
#112
0$
#113
b111001 f
b10 R
1$
#114
0$
#115
b11 R
b111010 f
1$
#116
0$
#117
b111011 f
b100 R
b1000001010001000100011 *
b1000001010001000100011 2
b1000001010001000100011 X
b0 +
b0 3
b0 I
b0 V
1$
#118
0$
#119
b0 R
b110000 D
b111100 f
b1000001000000000000000000000000 *
b1000001000000000000000000000000 2
b1000001000000000000000000000000 X
b100 +
b100 3
b100 I
b100 V
1$
#120
0$
#121
b111101 f
b1 R
b110100 E
b110000 -
b110000 5
b110000 G
b110000 U
1$
#122
0$
#123
b10 R
b111110 f
1$
#124
0$
#125
b111111 f
b11 R
1$
#126
0$
#127
b100 R
b1000000 f
b1000001010001000100011 *
b1000001010001000100011 2
b1000001010001000100011 X
b0 +
b0 3
b0 I
b0 V
1$
#128
0$
#129
b1000001 f
b0 R
b110100 D
b1000001000000000000000000000000 *
b1000001000000000000000000000000 2
b1000001000000000000000000000000 X
b100 +
b100 3
b100 I
b100 V
1$
#130
0$
#131
b1 R
b111000 E
b110100 -
b110100 5
b110100 G
b110100 U
b1000010 f
1$
#132
0$
#133
b1000011 f
b10 R
1$
#134
0$
#135
b11 R
b1000100 f
1$
#136
0$
#137
b1000101 f
b100 R
b1000001010001000100011 *
b1000001010001000100011 2
b1000001010001000100011 X
b0 +
b0 3
b0 I
b0 V
1$
#138
0$
#139
b0 R
b111000 D
b1000110 f
b1000001000000000000000000000000 *
b1000001000000000000000000000000 2
b1000001000000000000000000000000 X
b100 +
b100 3
b100 I
b100 V
1$
#140
0$
#141
b1000111 f
b1 R
b111100 E
b111000 -
b111000 5
b111000 G
b111000 U
1$
#142
0$
#143
b10 R
b1001000 f
1$
#144
0$
#145
b1001001 f
b11 R
1$
#146
0$
#147
b100 R
b1001010 f
b1000001010001000100011 *
b1000001010001000100011 2
b1000001010001000100011 X
b0 +
b0 3
b0 I
b0 V
1$
#148
0$
#149
b1001011 f
b0 R
b111100 D
b1000001000000000000000000000000 *
b1000001000000000000000000000000 2
b1000001000000000000000000000000 X
b100 +
b100 3
b100 I
b100 V
1$
#150
0$
#151
b1 R
b1000000 E
b111100 -
b111100 5
b111100 G
b111100 U
b1001100 f
1$
#152
0$
#153
b1001101 f
b10 R
1$
#154
0$
#155
b11 R
b1001110 f
1$
#156
0$
#157
b1001111 f
b100 R
b1000001010001000100011 *
b1000001010001000100011 2
b1000001010001000100011 X
b0 +
b0 3
b0 I
b0 V
1$
#158
0$
#159
b0 R
b1000000 D
b1010000 f
b1000001000000000000000000000000 *
b1000001000000000000000000000000 2
b1000001000000000000000000000000 X
b100 +
b100 3
b100 I
b100 V
1$
#160
0$
#161
b1010001 f
b1 R
b1000100 E
bx ,
bx 4
bx Y
b1000000 -
b1000000 5
b1000000 G
b1000000 U
1$
#162
0$
#163
b10 R
b1010010 f
1$
#164
0$
#165
b1010011 f
b11 R
1$
#166
0$
#167
b100 R
b1010100 f
b1000001010001000100011 *
b1000001010001000100011 2
b1000001010001000100011 X
b0 +
b0 3
b0 I
b0 V
1$
#168
0$
#169
b1010101 f
b0 R
b1000100 D
b1000001000000000000000000000000 *
b1000001000000000000000000000000 2
b1000001000000000000000000000000 X
b100 +
b100 3
b100 I
b100 V
1$
#170
0$
#171
b1 R
b1001000 E
bx H
b1000100 -
b1000100 5
b1000100 G
b1000100 U
b1010110 f
1$
#172
0$
#173
b1010111 f
b10 R
bx P
bx @
bx /
bx O
bx .
bx N
bx0 B
bx S
b0xxxxxxxxxxxx =
bx ?
bx >
bx F
bx C
1$
#174
0$
#175
b11 R
b1011000 f
bx <
1$
#176
0$
#177
b1011001 f
b100 R
bx &
bx 1
bx W
bx L
x%
xM
bx *
bx 2
bx X
bx +
bx 3
bx I
bx V
1$
#178
0$
#179
b0 R
0%
0M
b1001000 D
b1011010 f
b1000001000000000000000000000000 *
b1000001000000000000000000000000 2
b1000001000000000000000000000000 X
b100 +
b100 3
b100 I
b100 V
1$
#180
0$
#181
b1011011 f
b1 R
b1001100 E
b1001000 -
b1001000 5
b1001000 G
b1001000 U
1$
#182
0$
#183
b10 R
b0xxxxxxxxxxxxxxxxxxxxxxxxxxxxxxx Q
b0xxxxxxxxxxxxxxxxxxxxxxxxxxxxxxx A
b1011100 f
1$
#184
0$
#185
b1011101 f
b11 R
1$
#186
0$
#187
b100 R
b1011110 f
x%
xM
bx *
bx 2
bx X
bx +
bx 3
bx I
bx V
1$
#188
0$
#189
b1011111 f
b0 R
0%
0M
b1001100 D
b1000001000000000000000000000000 *
b1000001000000000000000000000000 2
b1000001000000000000000000000000 X
b100 +
b100 3
b100 I
b100 V
1$
#190
0$
#191
b1 R
b1010000 E
b1001100 -
b1001100 5
b1001100 G
b1001100 U
b1100000 f
1$
#192
0$
#193
b1100001 f
b10 R
1$
#194
0$
#195
b11 R
b1100010 f
1$
#196
0$
#197
b1100011 f
b100 R
x%
xM
bx *
bx 2
bx X
bx +
bx 3
bx I
bx V
1$
#198
0$
#199
b0 R
0%
0M
b1010000 D
b1100100 f
b1000001000000000000000000000000 *
b1000001000000000000000000000000 2
b1000001000000000000000000000000 X
b100 +
b100 3
b100 I
b100 V
1$
#200
0$
#201
b1100101 f
b1 R
b1010100 E
b1010000 -
b1010000 5
b1010000 G
b1010000 U
1$
#202
0$
#203
b10 R
b1100110 f
1$
#204
0$
#205
b1100111 f
b11 R
1$
#206
0$
#207
b100 R
b1101000 f
x%
xM
bx *
bx 2
bx X
bx +
bx 3
bx I
bx V
1$
#208
0$
#209
b1101001 f
b0 R
0%
0M
b1010100 D
b1000001000000000000000000000000 *
b1000001000000000000000000000000 2
b1000001000000000000000000000000 X
b100 +
b100 3
b100 I
b100 V
1$
#210
0$
#211
b1 R
b1011000 E
b1010100 -
b1010100 5
b1010100 G
b1010100 U
b1101010 f
1$
#212
0$
#213
b1101011 f
b10 R
1$
#214
0$
#215
b11 R
b1101100 f
1$
#216
0$
#217
b1101101 f
b100 R
x%
xM
bx *
bx 2
bx X
bx +
bx 3
bx I
bx V
1$
#218
0$
#219
b0 R
0%
0M
b1011000 D
b1101110 f
b1000001000000000000000000000000 *
b1000001000000000000000000000000 2
b1000001000000000000000000000000 X
b100 +
b100 3
b100 I
b100 V
1$
#220
0$
#221
b1101111 f
b1 R
b1011100 E
b1011000 -
b1011000 5
b1011000 G
b1011000 U
1$
#222
0$
#223
b10 R
b1110000 f
1$
#224
0$
#225
b1110001 f
b11 R
1$
#226
0$
#227
b100 R
b1110010 f
x%
xM
bx *
bx 2
bx X
bx +
bx 3
bx I
bx V
1$
#228
0$
#229
b1110011 f
b0 R
0%
0M
b1011100 D
b1000001000000000000000000000000 *
b1000001000000000000000000000000 2
b1000001000000000000000000000000 X
b100 +
b100 3
b100 I
b100 V
1$
#230
0$
#231
b1 R
b1100000 E
b1011100 -
b1011100 5
b1011100 G
b1011100 U
b1110100 f
1$
#232
0$
#233
b1110101 f
b10 R
1$
#234
0$
#235
b11 R
b1110110 f
1$
#236
0$
#237
b1110111 f
b100 R
x%
xM
bx *
bx 2
bx X
bx +
bx 3
bx I
bx V
1$
#238
0$
#239
b0 R
0%
0M
b1100000 D
b1111000 f
b1000001000000000000000000000000 *
b1000001000000000000000000000000 2
b1000001000000000000000000000000 X
b100 +
b100 3
b100 I
b100 V
1$
#240
0$
#241
b1111001 f
b1 R
b1100100 E
b1100000 -
b1100000 5
b1100000 G
b1100000 U
1$
#242
0$
#243
b10 R
b1111010 f
1$
#244
0$
#245
b1111011 f
b11 R
1$
#246
0$
#247
b100 R
b1111100 f
x%
xM
bx *
bx 2
bx X
bx +
bx 3
bx I
bx V
1$
#248
0$
#249
b1111101 f
b0 R
0%
0M
b1100100 D
b1000001000000000000000000000000 *
b1000001000000000000000000000000 2
b1000001000000000000000000000000 X
b100 +
b100 3
b100 I
b100 V
1$
#250
0$
#251
b1 R
b1101000 E
b1100100 -
b1100100 5
b1100100 G
b1100100 U
b1111110 f
1$
#252
0$
#253
b1111111 f
b10 R
1$
#254
0$
#255
b11 R
b10000000 f
1$
#256
0$
#257
b10000001 f
b100 R
x%
xM
bx *
bx 2
bx X
bx +
bx 3
bx I
bx V
1$
#258
0$
#259
b0 R
0%
0M
b1101000 D
b10000010 f
b1000001000000000000000000000000 *
b1000001000000000000000000000000 2
b1000001000000000000000000000000 X
b100 +
b100 3
b100 I
b100 V
1$
#260
0$
#261
b10000011 f
b1 R
b1101100 E
b1101000 -
b1101000 5
b1101000 G
b1101000 U
1$
#262
0$
#263
b10 R
b10000100 f
1$
#264
0$
#265
b10000101 f
b11 R
1$
#266
0$
#267
b100 R
b10000110 f
x%
xM
bx *
bx 2
bx X
bx +
bx 3
bx I
bx V
1$
#268
0$
#269
b10000111 f
b0 R
0%
0M
b1101100 D
b1000001000000000000000000000000 *
b1000001000000000000000000000000 2
b1000001000000000000000000000000 X
b100 +
b100 3
b100 I
b100 V
1$
#270
0$
#271
b1 R
b1110000 E
b1101100 -
b1101100 5
b1101100 G
b1101100 U
b10001000 f
1$
#272
0$
#273
b10001001 f
b10 R
1$
#274
0$
#275
b11 R
b10001010 f
1$
#276
0$
#277
b10001011 f
b100 R
x%
xM
bx *
bx 2
bx X
bx +
bx 3
bx I
bx V
1$
#278
0$
#279
b0 R
0%
0M
b1110000 D
b10001100 f
b1000001000000000000000000000000 *
b1000001000000000000000000000000 2
b1000001000000000000000000000000 X
b100 +
b100 3
b100 I
b100 V
1$
#280
0$
#281
b10001101 f
b1 R
b1110100 E
b1110000 -
b1110000 5
b1110000 G
b1110000 U
1$
#282
0$
#283
b10 R
b10001110 f
1$
#284
0$
#285
b10001111 f
b11 R
1$
#286
0$
#287
b100 R
b10010000 f
x%
xM
bx *
bx 2
bx X
bx +
bx 3
bx I
bx V
1$
#288
0$
